{"nodes":[{"nodeID":"42523","text":"Neil thinks about someone who Neil met a couple of years ago who is a young guy, about Neil's age","type":"I","timestamp":"2014-11-13 14:57:54"},{"nodeID":"42525","text":"Neil :  I think about someone who I met a couple of years ago who is a young guy, about my age","type":"L","timestamp":"2014-11-13 14:57:54"},{"nodeID":"42528","text":"Neil : he\u2019d lost his job at Tesco","type":"L","timestamp":"2014-11-13 14:57:54"},{"nodeID":"42532","text":"Neil :  mainly because he wasn\u2019t turning up to work on time","type":"L","timestamp":"2014-11-13 14:57:54"},{"nodeID":"42538","text":"Neil : which is mainly because he was smoking a lot of spliff","type":"L","timestamp":"2014-11-13 14:57:55"},{"nodeID":"42544","text":"Neil : and he was basically very disorganised","type":"L","timestamp":"2014-11-13 14:57:55"},{"nodeID":"42545","text":"This guy\u2019s just a scrounger, he needs a kick up the backside to get going","type":"I","timestamp":"2014-11-13 14:57:55"},{"nodeID":"42547","text":"some people : This guy\u2019s just a scrounger, he needs a kick up the backside to get going","type":"L","timestamp":"2014-11-13 14:57:55"},{"nodeID":"42549","text":"Neil : some people : This guy\u2019s just a scrounger, he needs a kick up the backside to get going","type":"L","timestamp":"2014-11-13 14:57:55"},{"nodeID":"42553","text":"we need to think about, how we have a more paternalist system for people like that","type":"I","timestamp":"2014-11-13 14:57:55"},{"nodeID":"42555","text":"Neil : Actually, we need to think about, how we have a more paternalist system for people like that","type":"L","timestamp":"2014-11-13 14:57:55"},{"nodeID":"42559","text":"If you took the people around this table this evening, and you took away all of our contacts, our qualifications our great jobs and so on, we\u2019d still have more internal resources than that guy","type":"I","timestamp":"2014-11-13 14:57:55"},{"nodeID":"42564","text":"We\u2019d still be much better off","type":"I","timestamp":"2014-11-13 14:57:55"},{"nodeID":"42566","text":"Neil : We\u2019d still be much better off","type":"L","timestamp":"2014-11-13 14:57:55"},{"nodeID":"42570","text":"we\u2019ve had the benefits, whatever they are, from our family of being set up in such a way that we understand the world of working and how to get on in life","type":"I","timestamp":"2014-11-13 14:57:55"},{"nodeID":"42572","text":"Neil : because we\u2019ve had the benefits, whatever they are, from our family of being set up in such a way that we understand the world of working and how to get on in life","type":"L","timestamp":"2014-11-13 14:57:55"},{"nodeID":"42576","text":"the reality is that in the last ten or twenty years there\u2019s been a massive transfer of wealth from the poor to the rich, and from the young to the old, and that what Neil's really trying to do is to justify that by blaming the poor for their position","type":"I","timestamp":"2014-11-13 14:57:55"},{"nodeID":"42578","text":"Clifford : Isn\u2019t the reality that in the last ten or twenty years there\u2019s been a massive transfer of wealth from the poor to the rich, and from the young to the old, and that what you\u2019re really trying to do is to justify that by blaming the poor for their position?","type":"L","timestamp":"2014-11-13 14:57:55"},{"nodeID":"42579","text":"Neil's not trying to justify anything","type":"I","timestamp":"2014-11-13 14:57:55"},{"nodeID":"42581","text":"Neil : No, I\u2019m not trying to justify anything","type":"L","timestamp":"2014-11-13 14:57:56"},{"nodeID":"42585","text":"there\u2019s been a transfer","type":"I","timestamp":"2014-11-13 14:57:56"},{"nodeID":"42587","text":"Clifford : But you agree that there\u2019s been a transfer?","type":"L","timestamp":"2014-11-13 14:57:56"},{"nodeID":"42591","text":"there has not been a transfer","type":"I","timestamp":"2014-11-13 14:57:56"},{"nodeID":"42592","text":"Neil : No","type":"L","timestamp":"2014-11-13 14:57:56"},{"nodeID":"42642","text":"what\u2019s happened is, there\u2019s been a huge and permanent increase in the number of people who are unemployed","type":"I","timestamp":"2014-11-14 12:10:46"},{"nodeID":"42644","text":"Neil : I think what\u2019s happened is, there\u2019s been a huge and permanent increase in the number of people who are unemployed","type":"L","timestamp":"2014-11-14 12:10:46"},{"nodeID":"42648","text":"We kidded ourselves during the last decade that we\u2019d solved the problem of unemployment,","type":"I","timestamp":"2014-11-14 12:10:46"},{"nodeID":"42650","text":"Neil : We kidded ourselves during the last decade that we\u2019d solved the problem of unemployment,","type":"L","timestamp":"2014-11-14 12:10:46"},{"nodeID":"42651","text":"we were just looking at the claimant count, a very narrow measure of unemployment","type":"I","timestamp":"2014-11-14 12:10:46"},{"nodeID":"42653","text":"Neil : because we were just looking at the claimant count, a very narrow measure of unemployment","type":"L","timestamp":"2014-11-14 12:10:46"},{"nodeID":"42657","text":"If you look at the wider measure of all the people on benefits: the people on incapacity benefit, the people on income support as well. Actually, even all the way through the years of the debt fuelled boom we had about 5 million people effectively workless","type":"I","timestamp":"2014-11-14 12:10:46"},{"nodeID":"42659","text":"Neil : If you look at the wider measure of all the people on benefits: the people on incapacity benefit, the people on income support as well. Actually, even all the way through the years of the debt fuelled boom we had about 5 million people effectively workless","type":"L","timestamp":"2014-11-14 12:10:46"},{"nodeID":"42660","text":"We need to think much harder about how we can make the benefit system, the whole welfare state much more activating, how we can help to get those people into work","type":"I","timestamp":"2014-11-14 12:10:46"},{"nodeID":"42662","text":"Neil : We need to think much harder about how we can make the benefit system, the whole welfare state much more activating, how we can help to get those people into work","type":"L","timestamp":"2014-11-14 12:10:46"},{"nodeID":"117047","text":"Asserting","type":"YA","timestamp":"2015-12-04 12:02:51","scheme":"Asserting","schemeID":"74"},{"nodeID":"117048","text":"the young guy\u2019d lost his job at Tesco","type":"I","timestamp":"2015-12-04 12:02:51"},{"nodeID":"117049","text":"Asserting","type":"YA","timestamp":"2015-12-04 12:02:51","scheme":"Asserting","schemeID":"74"},{"nodeID":"117050","text":"TA","type":"TA","timestamp":"2015-12-04 12:02:51"},{"nodeID":"117051","text":"the young guy wasn\u2019t turning up to work on time","type":"I","timestamp":"2015-12-04 12:02:51"},{"nodeID":"117052","text":"Asserting","type":"YA","timestamp":"2015-12-04 12:02:52","scheme":"Asserting","schemeID":"74"},{"nodeID":"117053","text":"TA","type":"TA","timestamp":"2015-12-04 12:02:52"},{"nodeID":"117054","text":"Default Inference","type":"RA","timestamp":"2015-12-04 12:02:52","scheme":"Default Inference","schemeID":"72"},{"nodeID":"117055","text":"Arguing","type":"YA","timestamp":"2015-12-04 12:02:52","scheme":"Arguing","schemeID":"80"},{"nodeID":"117056","text":"the young guy was smoking a lot of spliff","type":"I","timestamp":"2015-12-04 12:02:52"},{"nodeID":"117057","text":"Asserting","type":"YA","timestamp":"2015-12-04 12:02:52","scheme":"Asserting","schemeID":"74"},{"nodeID":"117058","text":"the young guy was basically very disorganized","type":"I","timestamp":"2015-12-04 12:02:52"},{"nodeID":"117059","text":"Asserting","type":"YA","timestamp":"2015-12-04 12:02:52","scheme":"Asserting","schemeID":"74"},{"nodeID":"117060","text":"Asserting","type":"YA","timestamp":"2015-12-04 12:02:52","scheme":"Asserting","schemeID":"74"},{"nodeID":"117061","text":"Asserting","type":"YA","timestamp":"2015-12-04 12:02:52","scheme":"Asserting","schemeID":"74"},{"nodeID":"117062","text":"TA","type":"TA","timestamp":"2015-12-04 12:02:52"},{"nodeID":"117063","text":"Default Inference","type":"RA","timestamp":"2015-12-04 12:02:52","scheme":"Default Inference","schemeID":"72"},{"nodeID":"117064","text":"Arguing","type":"YA","timestamp":"2015-12-04 12:02:53","scheme":"Arguing","schemeID":"80"},{"nodeID":"117065","text":"Asserting","type":"YA","timestamp":"2015-12-04 12:02:53","scheme":"Asserting","schemeID":"74"},{"nodeID":"117066","text":"TA","type":"TA","timestamp":"2015-12-04 12:02:53"},{"nodeID":"117067","text":"Asserting","type":"YA","timestamp":"2015-12-04 12:02:53","scheme":"Asserting","schemeID":"74"},{"nodeID":"117068","text":"TA","type":"TA","timestamp":"2015-12-04 12:02:53"},{"nodeID":"117069","text":"Default Inference","type":"RA","timestamp":"2015-12-04 12:02:53","scheme":"Default Inference","schemeID":"72"},{"nodeID":"117070","text":"Arguing","type":"YA","timestamp":"2015-12-04 12:02:53","scheme":"Arguing","schemeID":"80"},{"nodeID":"117071","text":"Asserting","type":"YA","timestamp":"2015-12-04 12:02:53","scheme":"Asserting","schemeID":"74"},{"nodeID":"117072","text":"TA","type":"TA","timestamp":"2015-12-04 12:02:53"},{"nodeID":"117073","text":"Default Rephrase","type":"MA","timestamp":"2015-12-04 12:02:53","scheme":"Default Rephrase","schemeID":"144"},{"nodeID":"117074","text":"Default Illocuting","type":"YA","timestamp":"2015-12-04 12:02:53","scheme":"Default Illocuting","schemeID":"168"},{"nodeID":"117075","text":"Asserting","type":"YA","timestamp":"2015-12-04 12:02:54","scheme":"Asserting","schemeID":"74"},{"nodeID":"117076","text":"TA","type":"TA","timestamp":"2015-12-04 12:02:54"},{"nodeID":"117077","text":"Assertive Questioning","type":"YA","timestamp":"2015-12-04 12:02:54","scheme":"AssertiveQuestioning","schemeID":"73"},{"nodeID":"117078","text":"Assertive Questioning","type":"YA","timestamp":"2015-12-04 12:02:54","scheme":"AssertiveQuestioning","schemeID":"73"},{"nodeID":"117079","text":"TA","type":"TA","timestamp":"2015-12-04 12:02:54"},{"nodeID":"117080","text":"Asserting","type":"YA","timestamp":"2015-12-04 12:02:54","scheme":"Asserting","schemeID":"74"},{"nodeID":"117081","text":"Default Conflict","type":"CA","timestamp":"2015-12-04 12:02:54","scheme":"Default Conflict","schemeID":"71"},{"nodeID":"117082","text":"Disagreeing","type":"YA","timestamp":"2015-12-04 12:02:54","scheme":"Disagreeing","schemeID":"78"},{"nodeID":"117083","text":"Asserting","type":"YA","timestamp":"2015-12-04 12:02:54","scheme":"Asserting","schemeID":"74"},{"nodeID":"117084","text":"TA","type":"TA","timestamp":"2015-12-04 12:02:55"},{"nodeID":"117085","text":"Default Inference","type":"RA","timestamp":"2015-12-04 12:02:55","scheme":"Default Inference","schemeID":"72"},{"nodeID":"117086","text":"Arguing","type":"YA","timestamp":"2015-12-04 12:02:55","scheme":"Arguing","schemeID":"80"},{"nodeID":"117087","text":"Asserting","type":"YA","timestamp":"2015-12-04 12:02:55","scheme":"Asserting","schemeID":"74"},{"nodeID":"117088","text":"Asserting","type":"YA","timestamp":"2015-12-04 12:02:55","scheme":"Asserting","schemeID":"74"},{"nodeID":"117089","text":"TA","type":"TA","timestamp":"2015-12-04 12:02:55"},{"nodeID":"117090","text":"Default Inference","type":"RA","timestamp":"2015-12-04 12:02:55","scheme":"Default Inference","schemeID":"72"},{"nodeID":"117091","text":"Arguing","type":"YA","timestamp":"2015-12-04 12:02:55","scheme":"Arguing","schemeID":"80"},{"nodeID":"117092","text":"Asserting","type":"YA","timestamp":"2015-12-04 12:02:55","scheme":"Asserting","schemeID":"74"},{"nodeID":"117093","text":"Asserting","type":"YA","timestamp":"2015-12-04 12:02:55","scheme":"Asserting","schemeID":"74"},{"nodeID":"117094","text":"TA","type":"TA","timestamp":"2015-12-04 12:02:56"},{"nodeID":"117095","text":"Default Inference","type":"RA","timestamp":"2015-12-04 12:02:56","scheme":"Default Inference","schemeID":"72"},{"nodeID":"117096","text":"Arguing","type":"YA","timestamp":"2015-12-04 12:02:56","scheme":"Arguing","schemeID":"80"},{"nodeID":"117097","text":"Default Transition","type":"TA","timestamp":"2015-12-04 12:02:56","scheme":"Default Transition","schemeID":"82"},{"nodeID":"117098","text":"Default Inference","type":"RA","timestamp":"2015-12-04 12:02:56","scheme":"Default Inference","schemeID":"72"},{"nodeID":"117099","text":"Arguing","type":"YA","timestamp":"2015-12-04 12:02:56","scheme":"Arguing","schemeID":"80"},{"nodeID":"117100","text":"Default Conflict","type":"CA","timestamp":"2015-12-04 12:02:56","scheme":"Default Conflict","schemeID":"71"},{"nodeID":"117101","text":"Disagreeing","type":"YA","timestamp":"2015-12-04 12:02:56","scheme":"Disagreeing","schemeID":"78"},{"nodeID":"117102","text":"Default Inference","type":"RA","timestamp":"2015-12-04 12:02:56","scheme":"Default Inference","schemeID":"72"},{"nodeID":"117103","text":"Arguing","type":"YA","timestamp":"2015-12-04 12:02:56","scheme":"Arguing","schemeID":"80"},{"nodeID":"117104","text":"Default Transition","type":"TA","timestamp":"2015-12-04 12:02:56","scheme":"Default Transition","schemeID":"82"},{"nodeID":"117105","text":"Default Conflict","type":"CA","timestamp":"2015-12-04 12:02:56","scheme":"Default Conflict","schemeID":"71"},{"nodeID":"117106","text":"Disagreeing","type":"YA","timestamp":"2015-12-04 12:02:56","scheme":"Disagreeing","schemeID":"78"},{"nodeID":"117107","text":"M: Neil : No","type":"L","timestamp":"2015-12-04 12:02:56"},{"nodeID":"117108","text":"Asserting","type":"YA","timestamp":"2015-12-04 12:02:56","scheme":"Asserting","schemeID":"74"},{"nodeID":"117109","text":"M: Neil : No, I\u2019m not trying to justify anything","type":"L","timestamp":"2015-12-04 12:02:56"},{"nodeID":"117110","text":"Default Transition","type":"TA","timestamp":"2015-12-04 12:02:56","scheme":"Default Transition","schemeID":"82"},{"nodeID":"117111","text":"Default Conflict","type":"CA","timestamp":"2015-12-04 12:02:57","scheme":"Default Conflict","schemeID":"71"},{"nodeID":"117112","text":"Disagreeing","type":"YA","timestamp":"2015-12-04 12:02:57","scheme":"Disagreeing","schemeID":"78"},{"nodeID":"117113","text":"Default Transition","type":"TA","timestamp":"2015-12-04 12:02:57","scheme":"Default Transition","schemeID":"82"},{"nodeID":"117114","text":"Default Rephrase","type":"MA","timestamp":"2015-12-04 12:02:57","scheme":"Default Rephrase","schemeID":"144"},{"nodeID":"117115","text":"Default Illocuting","type":"YA","timestamp":"2015-12-04 12:02:57","scheme":"Default Illocuting","schemeID":"168"}],"edges":[{"edgeID":"156367","fromID":"117047","toID":"42523","formEdgeID":null},{"edgeID":"156368","fromID":"42525","toID":"117047","formEdgeID":null},{"edgeID":"156369","fromID":"117049","toID":"117048","formEdgeID":null},{"edgeID":"156370","fromID":"42528","toID":"117049","formEdgeID":null},{"edgeID":"156371","fromID":"42525","toID":"117050","formEdgeID":null},{"edgeID":"156372","fromID":"117050","toID":"42528","formEdgeID":null},{"edgeID":"156373","fromID":"117052","toID":"117051","formEdgeID":null},{"edgeID":"156374","fromID":"42532","toID":"117052","formEdgeID":null},{"edgeID":"156375","fromID":"42528","toID":"117053","formEdgeID":null},{"edgeID":"156376","fromID":"117053","toID":"42532","formEdgeID":null},{"edgeID":"156377","fromID":"117051","toID":"117054","formEdgeID":null},{"edgeID":"156378","fromID":"117054","toID":"117048","formEdgeID":null},{"edgeID":"156379","fromID":"117053","toID":"117055","formEdgeID":null},{"edgeID":"156380","fromID":"117055","toID":"117054","formEdgeID":null},{"edgeID":"156381","fromID":"117057","toID":"117056","formEdgeID":null},{"edgeID":"156382","fromID":"42538","toID":"117057","formEdgeID":null},{"edgeID":"156383","fromID":"117059","toID":"117058","formEdgeID":null},{"edgeID":"156384","fromID":"42544","toID":"117059","formEdgeID":null},{"edgeID":"156385","fromID":"117060","toID":"42545","formEdgeID":null},{"edgeID":"156386","fromID":"42547","toID":"117060","formEdgeID":null},{"edgeID":"156387","fromID":"117061","toID":"42547","formEdgeID":null},{"edgeID":"156388","fromID":"42549","toID":"117061","formEdgeID":null},{"edgeID":"156389","fromID":"42538","toID":"117062","formEdgeID":null},{"edgeID":"156390","fromID":"117062","toID":"42549","formEdgeID":null},{"edgeID":"156391","fromID":"42545","toID":"117063","formEdgeID":null},{"edgeID":"156392","fromID":"117063","toID":"117056","formEdgeID":null},{"edgeID":"156393","fromID":"117062","toID":"117064","formEdgeID":null},{"edgeID":"156394","fromID":"117064","toID":"117063","formEdgeID":null},{"edgeID":"156395","fromID":"117065","toID":"42553","formEdgeID":null},{"edgeID":"156396","fromID":"42555","toID":"117065","formEdgeID":null},{"edgeID":"156397","fromID":"42549","toID":"117066","formEdgeID":null},{"edgeID":"156398","fromID":"117066","toID":"42555","formEdgeID":null},{"edgeID":"156399","fromID":"117067","toID":"42559","formEdgeID":null},{"edgeID":"156400","fromID":"42559","toID":"117067","formEdgeID":null},{"edgeID":"156401","fromID":"42555","toID":"117068","formEdgeID":null},{"edgeID":"156402","fromID":"117068","toID":"42559","formEdgeID":null},{"edgeID":"156403","fromID":"42559","toID":"117069","formEdgeID":null},{"edgeID":"156404","fromID":"117069","toID":"42553","formEdgeID":null},{"edgeID":"156405","fromID":"117068","toID":"117070","formEdgeID":null},{"edgeID":"156406","fromID":"117070","toID":"117069","formEdgeID":null},{"edgeID":"156407","fromID":"117071","toID":"42564","formEdgeID":null},{"edgeID":"156408","fromID":"42566","toID":"117071","formEdgeID":null},{"edgeID":"156409","fromID":"42559","toID":"117072","formEdgeID":null},{"edgeID":"156410","fromID":"117072","toID":"42566","formEdgeID":null},{"edgeID":"156411","fromID":"42564","toID":"117073","formEdgeID":null},{"edgeID":"156412","fromID":"117073","toID":"42559","formEdgeID":null},{"edgeID":"156413","fromID":"117072","toID":"117074","formEdgeID":null},{"edgeID":"156414","fromID":"117074","toID":"117073","formEdgeID":null},{"edgeID":"156415","fromID":"117075","toID":"42570","formEdgeID":null},{"edgeID":"156416","fromID":"42572","toID":"117075","formEdgeID":null},{"edgeID":"156417","fromID":"42566","toID":"117076","formEdgeID":null},{"edgeID":"156418","fromID":"117076","toID":"42572","formEdgeID":null},{"edgeID":"156419","fromID":"117077","toID":"42576","formEdgeID":null},{"edgeID":"156420","fromID":"42578","toID":"117077","formEdgeID":null},{"edgeID":"156421","fromID":"117078","toID":"42585","formEdgeID":null},{"edgeID":"156422","fromID":"42587","toID":"117078","formEdgeID":null},{"edgeID":"156423","fromID":"42587","toID":"117079","formEdgeID":null},{"edgeID":"156424","fromID":"117079","toID":"42592","formEdgeID":null},{"edgeID":"156425","fromID":"117079","toID":"117080","formEdgeID":null},{"edgeID":"156426","fromID":"117080","toID":"42591","formEdgeID":null},{"edgeID":"156427","fromID":"42591","toID":"117081","formEdgeID":null},{"edgeID":"156428","fromID":"117081","toID":"42585","formEdgeID":null},{"edgeID":"156429","fromID":"117079","toID":"117082","formEdgeID":null},{"edgeID":"156430","fromID":"117082","toID":"117081","formEdgeID":null},{"edgeID":"156431","fromID":"117083","toID":"42642","formEdgeID":null},{"edgeID":"156432","fromID":"42644","toID":"117083","formEdgeID":null},{"edgeID":"156433","fromID":"42592","toID":"117084","formEdgeID":null},{"edgeID":"156434","fromID":"117084","toID":"42644","formEdgeID":null},{"edgeID":"156435","fromID":"42642","toID":"117085","formEdgeID":null},{"edgeID":"156436","fromID":"117085","toID":"42591","formEdgeID":null},{"edgeID":"156437","fromID":"117084","toID":"117086","formEdgeID":null},{"edgeID":"156438","fromID":"117086","toID":"117085","formEdgeID":null},{"edgeID":"156439","fromID":"117087","toID":"42648","formEdgeID":null},{"edgeID":"156440","fromID":"42650","toID":"117087","formEdgeID":null},{"edgeID":"156441","fromID":"117084","toID":"42650","formEdgeID":null},{"edgeID":"156442","fromID":"42648","toID":"117085","formEdgeID":null},{"edgeID":"156443","fromID":"117088","toID":"42651","formEdgeID":null},{"edgeID":"156444","fromID":"42653","toID":"117088","formEdgeID":null},{"edgeID":"156445","fromID":"42650","toID":"117089","formEdgeID":null},{"edgeID":"156446","fromID":"117089","toID":"42653","formEdgeID":null},{"edgeID":"156447","fromID":"42651","toID":"117090","formEdgeID":null},{"edgeID":"156448","fromID":"117090","toID":"42648","formEdgeID":null},{"edgeID":"156449","fromID":"117089","toID":"117091","formEdgeID":null},{"edgeID":"156450","fromID":"117091","toID":"117090","formEdgeID":null},{"edgeID":"156451","fromID":"117092","toID":"42657","formEdgeID":null},{"edgeID":"156452","fromID":"42659","toID":"117092","formEdgeID":null},{"edgeID":"156453","fromID":"117089","toID":"42659","formEdgeID":null},{"edgeID":"156454","fromID":"42657","toID":"117090","formEdgeID":null},{"edgeID":"156455","fromID":"117093","toID":"42660","formEdgeID":null},{"edgeID":"156456","fromID":"42662","toID":"117093","formEdgeID":null},{"edgeID":"156457","fromID":"42659","toID":"117094","formEdgeID":null},{"edgeID":"156458","fromID":"117094","toID":"42662","formEdgeID":null},{"edgeID":"156459","fromID":"42657","toID":"117095","formEdgeID":null},{"edgeID":"156460","fromID":"117095","toID":"42660","formEdgeID":null},{"edgeID":"156461","fromID":"117094","toID":"117096","formEdgeID":null},{"edgeID":"156462","fromID":"117096","toID":"117095","formEdgeID":null},{"edgeID":"156463","fromID":"42532","toID":"117097","formEdgeID":null},{"edgeID":"156464","fromID":"117097","toID":"42538","formEdgeID":null},{"edgeID":"156465","fromID":"117056","toID":"117098","formEdgeID":null},{"edgeID":"156466","fromID":"117098","toID":"117051","formEdgeID":null},{"edgeID":"156467","fromID":"117097","toID":"117099","formEdgeID":null},{"edgeID":"156468","fromID":"117099","toID":"117098","formEdgeID":null},{"edgeID":"156469","fromID":"117053","toID":"42544","formEdgeID":null},{"edgeID":"156470","fromID":"117058","toID":"117054","formEdgeID":null},{"edgeID":"156471","fromID":"42553","toID":"117100","formEdgeID":null},{"edgeID":"156472","fromID":"117100","toID":"42545","formEdgeID":null},{"edgeID":"156473","fromID":"117066","toID":"117101","formEdgeID":null},{"edgeID":"156474","fromID":"117101","toID":"117100","formEdgeID":null},{"edgeID":"156475","fromID":"42570","toID":"117102","formEdgeID":null},{"edgeID":"156476","fromID":"117102","toID":"42564","formEdgeID":null},{"edgeID":"156477","fromID":"117076","toID":"117103","formEdgeID":null},{"edgeID":"156478","fromID":"117103","toID":"117102","formEdgeID":null},{"edgeID":"156479","fromID":"42559","toID":"117104","formEdgeID":null},{"edgeID":"156480","fromID":"117104","toID":"42578","formEdgeID":null},{"edgeID":"156481","fromID":"42576","toID":"117105","formEdgeID":null},{"edgeID":"156482","fromID":"117105","toID":"42559","formEdgeID":null},{"edgeID":"156483","fromID":"117104","toID":"117106","formEdgeID":null},{"edgeID":"156484","fromID":"117106","toID":"117105","formEdgeID":null},{"edgeID":"156485","fromID":"117108","toID":"42579","formEdgeID":null},{"edgeID":"156486","fromID":"42581","toID":"117108","formEdgeID":null},{"edgeID":"156487","fromID":"42578","toID":"117110","formEdgeID":null},{"edgeID":"156488","fromID":"117110","toID":"42581","formEdgeID":null},{"edgeID":"156489","fromID":"42579","toID":"117111","formEdgeID":null},{"edgeID":"156490","fromID":"117111","toID":"42576","formEdgeID":null},{"edgeID":"156491","fromID":"117110","toID":"117112","formEdgeID":null},{"edgeID":"156492","fromID":"117112","toID":"117111","formEdgeID":null},{"edgeID":"156493","fromID":"42578","toID":"117113","formEdgeID":null},{"edgeID":"156494","fromID":"117113","toID":"42587","formEdgeID":null},{"edgeID":"156495","fromID":"42585","toID":"117114","formEdgeID":null},{"edgeID":"156496","fromID":"117114","toID":"42576","formEdgeID":null},{"edgeID":"156497","fromID":"117113","toID":"117115","formEdgeID":null},{"edgeID":"156498","fromID":"117115","toID":"117114","formEdgeID":null}],"locutions":[{"nodeID":"42525","personID":"588","timestamp":"2014-11-13 14:57:57","start":null,"end":null,"source":null},{"nodeID":"42528","personID":"588","timestamp":"2014-11-13 14:57:57","start":null,"end":null,"source":null},{"nodeID":"42532","personID":"588","timestamp":"2014-11-13 14:57:57","start":null,"end":null,"source":null},{"nodeID":"42538","personID":"588","timestamp":"2014-11-13 14:57:57","start":null,"end":null,"source":null},{"nodeID":"42544","personID":"588","timestamp":"2014-11-13 14:57:57","start":null,"end":null,"source":null},{"nodeID":"42547","personID":"589","timestamp":"2014-11-13 14:57:57","start":null,"end":null,"source":null},{"nodeID":"42549","personID":"588","timestamp":"2014-11-13 14:57:57","start":null,"end":null,"source":null},{"nodeID":"42555","personID":"588","timestamp":"2014-11-13 14:57:57","start":null,"end":null,"source":null},{"nodeID":"42559","personID":"588","timestamp":"2014-11-13 14:57:57","start":null,"end":null,"source":null},{"nodeID":"42566","personID":"588","timestamp":"2014-11-13 14:57:57","start":null,"end":null,"source":null},{"nodeID":"42572","personID":"588","timestamp":"2014-11-13 14:57:57","start":null,"end":null,"source":null},{"nodeID":"42578","personID":"4","timestamp":"2014-11-13 14:57:57","start":null,"end":null,"source":null},{"nodeID":"42581","personID":"588","timestamp":"2014-11-13 14:57:57","start":null,"end":null,"source":null},{"nodeID":"42587","personID":"4","timestamp":"2014-11-13 14:57:57","start":null,"end":null,"source":null},{"nodeID":"42592","personID":"588","timestamp":"2014-11-13 14:57:57","start":null,"end":null,"source":null},{"nodeID":"42644","personID":"590","timestamp":"2014-11-14 12:10:48","start":null,"end":null,"source":null},{"nodeID":"42650","personID":"590","timestamp":"2014-11-14 12:10:48","start":null,"end":null,"source":null},{"nodeID":"42653","personID":"590","timestamp":"2014-11-14 12:10:48","start":null,"end":null,"source":null},{"nodeID":"42659","personID":"590","timestamp":"2014-11-14 12:10:48","start":null,"end":null,"source":null},{"nodeID":"42662","personID":"590","timestamp":"2014-11-14 12:10:48","start":null,"end":null,"source":null},{"nodeID":"42525","personID":"1257","timestamp":"2015-11-11 12:17:16","start":null,"end":null,"source":null},{"nodeID":"42528","personID":"1257","timestamp":"2015-11-11 12:17:16","start":null,"end":null,"source":null},{"nodeID":"42532","personID":"1257","timestamp":"2015-11-11 12:17:16","start":null,"end":null,"source":null},{"nodeID":"42538","personID":"1257","timestamp":"2015-11-11 12:17:16","start":null,"end":null,"source":null},{"nodeID":"42544","personID":"1257","timestamp":"2015-11-11 12:17:16","start":null,"end":null,"source":null},{"nodeID":"42547","personID":"589","timestamp":"2015-11-11 12:17:16","start":null,"end":null,"source":null},{"nodeID":"42549","personID":"1257","timestamp":"2015-11-11 12:17:16","start":null,"end":null,"source":null},{"nodeID":"42555","personID":"1257","timestamp":"2015-11-11 12:17:16","start":null,"end":null,"source":null},{"nodeID":"42559","personID":"1257","timestamp":"2015-11-11 12:17:16","start":null,"end":null,"source":null},{"nodeID":"42566","personID":"1257","timestamp":"2015-11-11 12:17:16","start":null,"end":null,"source":null},{"nodeID":"42572","personID":"1257","timestamp":"2015-11-11 12:17:16","start":null,"end":null,"source":null},{"nodeID":"42578","personID":"4","timestamp":"2015-11-11 12:17:16","start":null,"end":null,"source":null},{"nodeID":"42581","personID":"1257","timestamp":"2015-11-11 12:17:16","start":null,"end":null,"source":null},{"nodeID":"42587","personID":"4","timestamp":"2015-11-11 12:17:16","start":null,"end":null,"source":null},{"nodeID":"42592","personID":"1257","timestamp":"2015-11-11 12:17:16","start":null,"end":null,"source":null},{"nodeID":"42644","personID":"1257","timestamp":"2015-11-11 12:17:16","start":null,"end":null,"source":null},{"nodeID":"42650","personID":"1257","timestamp":"2015-11-11 12:17:16","start":null,"end":null,"source":null},{"nodeID":"42653","personID":"1257","timestamp":"2015-11-11 12:17:16","start":null,"end":null,"source":null},{"nodeID":"42659","personID":"1257","timestamp":"2015-11-11 12:17:16","start":null,"end":null,"source":null},{"nodeID":"42662","personID":"1257","timestamp":"2015-11-11 12:17:16","start":null,"end":null,"source":null},{"nodeID":"42525","personID":"1293","timestamp":"2015-12-04 12:03:00","start":null,"end":null,"source":null},{"nodeID":"42528","personID":"1293","timestamp":"2015-12-04 12:03:00","start":null,"end":null,"source":null},{"nodeID":"42532","personID":"1293","timestamp":"2015-12-04 12:03:00","start":null,"end":null,"source":null},{"nodeID":"42538","personID":"1293","timestamp":"2015-12-04 12:03:00","start":null,"end":null,"source":null},{"nodeID":"42544","personID":"1293","timestamp":"2015-12-04 12:03:00","start":null,"end":null,"source":null},{"nodeID":"42547","personID":"589","timestamp":"2015-12-04 12:03:00","start":null,"end":null,"source":null},{"nodeID":"42549","personID":"1293","timestamp":"2015-12-04 12:03:00","start":null,"end":null,"source":null},{"nodeID":"42555","personID":"1293","timestamp":"2015-12-04 12:03:00","start":null,"end":null,"source":null},{"nodeID":"42559","personID":"1293","timestamp":"2015-12-04 12:03:00","start":null,"end":null,"source":null},{"nodeID":"42566","personID":"1293","timestamp":"2015-12-04 12:03:00","start":null,"end":null,"source":null},{"nodeID":"42572","personID":"1293","timestamp":"2015-12-04 12:03:00","start":null,"end":null,"source":null},{"nodeID":"42578","personID":"4","timestamp":"2015-12-04 12:03:00","start":null,"end":null,"source":null},{"nodeID":"42587","personID":"4","timestamp":"2015-12-04 12:03:00","start":null,"end":null,"source":null},{"nodeID":"42592","personID":"1293","timestamp":"2015-12-04 12:03:00","start":null,"end":null,"source":null},{"nodeID":"42644","personID":"1293","timestamp":"2015-12-04 12:03:00","start":null,"end":null,"source":null},{"nodeID":"42650","personID":"1293","timestamp":"2015-12-04 12:03:00","start":null,"end":null,"source":null},{"nodeID":"42653","personID":"1293","timestamp":"2015-12-04 12:03:00","start":null,"end":null,"source":null},{"nodeID":"42659","personID":"1293","timestamp":"2015-12-04 12:03:00","start":null,"end":null,"source":null},{"nodeID":"42662","personID":"1293","timestamp":"2015-12-04 12:03:00","start":null,"end":null,"source":null},{"nodeID":"42581","personID":"1293","timestamp":"2015-12-04 12:03:00","start":null,"end":null,"source":null}]}