{"nodes":[{"nodeID":"27416","text":"JB : Yes","type":"L","timestamp":"2014-02-28 14:38:39"},{"nodeID":"34497","text":"the fundamental duty we have as a society towards the unemployed is to make sure there are enough jobs for them to take the opportunity to go and work","type":"I","timestamp":"2014-08-12 12:44:47"},{"nodeID":"34499","text":"CL : Isn\u2019t the fundamental duty we have as a society towards the unemployed, to make sure there are enough jobs for them to take the opportunity to go and work?","type":"L","timestamp":"2014-08-12 12:44:47"},{"nodeID":"34500","text":"there\u2019s the rub","type":"I","timestamp":"2014-08-12 12:44:47"},{"nodeID":"34502","text":"JB : there\u2019s the rub","type":"L","timestamp":"2014-08-12 12:44:47"},{"nodeID":"34508","text":"there are lots of ways in which you can hopefully allow the market to create jobs","type":"I","timestamp":"2014-08-12 12:44:47"},{"nodeID":"34510","text":"JB : there are lots of ways in which you can hopefully allow the market to create jobs","type":"L","timestamp":"2014-08-12 12:44:47"},{"nodeID":"34514","text":"If the market doesn\u2019t, for whatever reason never mind who\u2019s fault it is, then the next thing that the government should do, is to provide jobs for these people to do","type":"I","timestamp":"2014-08-12 12:44:47"},{"nodeID":"34516","text":"JB : If the market doesn\u2019t, for whatever reason \u2013 and you\u2019re colleague may think it\u2019s because of the failure of Capitalism, I may think it\u2019s because of government interference \u2013 never mind who\u2019s fault it is, then the next thing that the government should do, is to provide jobs for these people to do","type":"L","timestamp":"2014-08-12 12:44:47"},{"nodeID":"34520","text":"If the market doesn\u2019t, for whatever reason it\u2019s because of the failure of Capitalism","type":"I","timestamp":"2014-08-12 12:44:48"},{"nodeID":"34522","text":"your colleague : If the market doesn\u2019t, for whatever reason \u2013 it\u2019s because of the failure of Capitalism","type":"L","timestamp":"2014-08-12 12:44:48"},{"nodeID":"34524","text":"JB : your colleague : If the market doesn\u2019t, for whatever reason \u2013 it\u2019s because of the failure of Capitalism","type":"L","timestamp":"2014-08-12 12:44:48"},{"nodeID":"34526","text":"it\u2019s because of government interference","type":"I","timestamp":"2014-08-12 12:44:48"},{"nodeID":"34528","text":"JB :  I may think it\u2019s because of government interference","type":"L","timestamp":"2014-08-12 12:44:48"},{"nodeID":"34532","text":"that undermines the whole argument that you make about incentives","type":"I","timestamp":"2014-08-12 12:44:48"},{"nodeID":"34534","text":"CL : But doesn\u2019t that undermine the whole argument that you make about incentives?","type":"L","timestamp":"2014-08-12 12:44:48"},{"nodeID":"34536","text":"If people want to work, if it\u2019s their nature to work, and if the work was there, then they\u2019d go and do it","type":"I","timestamp":"2014-08-12 12:44:48"},{"nodeID":"34538","text":"CL : If people want to work, if it\u2019s their nature to work, and if the work was there, then they\u2019d go and do it","type":"L","timestamp":"2014-08-12 12:44:48"},{"nodeID":"115901","text":"Assertive Questioning","type":"YA","timestamp":"2015-12-03 12:48:36","scheme":"AssertiveQuestioning","schemeID":"73"},{"nodeID":"115902","text":"Asserting","type":"YA","timestamp":"2015-12-03 12:48:36","scheme":"Asserting","schemeID":"74"},{"nodeID":"115903","text":"TA","type":"TA","timestamp":"2015-12-03 12:48:36"},{"nodeID":"115904","text":"TA","type":"TA","timestamp":"2015-12-03 12:48:36"},{"nodeID":"115905","text":"Agreeing","type":"YA","timestamp":"2015-12-03 12:48:36","scheme":"Agreeing","schemeID":"77"},{"nodeID":"115906","text":"Asserting","type":"YA","timestamp":"2015-12-03 12:48:36","scheme":"Asserting","schemeID":"74"},{"nodeID":"115907","text":"TA","type":"TA","timestamp":"2015-12-03 12:48:36"},{"nodeID":"115908","text":"RA","type":"RA","timestamp":"2015-12-03 12:48:36"},{"nodeID":"115909","text":"Arguing","type":"YA","timestamp":"2015-12-03 12:48:37","scheme":"Arguing","schemeID":"80"},{"nodeID":"115910","text":"Asserting","type":"YA","timestamp":"2015-12-03 12:48:37","scheme":"Asserting","schemeID":"74"},{"nodeID":"115911","text":"RA","type":"RA","timestamp":"2015-12-03 12:48:37"},{"nodeID":"115912","text":"TA","type":"TA","timestamp":"2015-12-03 12:48:37"},{"nodeID":"115913","text":"Arguing","type":"YA","timestamp":"2015-12-03 12:48:37","scheme":"Arguing","schemeID":"80"},{"nodeID":"115914","text":"Asserting","type":"YA","timestamp":"2015-12-03 12:48:37","scheme":"Asserting","schemeID":"74"},{"nodeID":"115915","text":"Asserting","type":"YA","timestamp":"2015-12-03 12:48:37","scheme":"Asserting","schemeID":"74"},{"nodeID":"115916","text":"TA","type":"TA","timestamp":"2015-12-03 12:48:37"},{"nodeID":"115917","text":"Asserting","type":"YA","timestamp":"2015-12-03 12:48:37","scheme":"Asserting","schemeID":"74"},{"nodeID":"115918","text":"TA","type":"TA","timestamp":"2015-12-03 12:48:37"},{"nodeID":"115919","text":"CA","type":"CA","timestamp":"2015-12-03 12:48:38"},{"nodeID":"115920","text":"Disagreeing","type":"YA","timestamp":"2015-12-03 12:48:38","scheme":"Disagreeing","schemeID":"78"},{"nodeID":"115921","text":"Assertive Questioning","type":"YA","timestamp":"2015-12-03 12:48:38","scheme":"AssertiveQuestioning","schemeID":"73"},{"nodeID":"115922","text":"TA","type":"TA","timestamp":"2015-12-03 12:48:38"},{"nodeID":"115923","text":"Asserting","type":"YA","timestamp":"2015-12-03 12:48:38","scheme":"Asserting","schemeID":"74"},{"nodeID":"115924","text":"TA","type":"TA","timestamp":"2015-12-03 12:48:38"},{"nodeID":"115925","text":"Default Conflict","type":"CA","timestamp":"2015-12-03 12:48:38","scheme":"Default Conflict","schemeID":"71"},{"nodeID":"115926","text":"Disagreeing","type":"YA","timestamp":"2015-12-03 12:48:38","scheme":"Disagreeing","schemeID":"78"},{"nodeID":"115927","text":"Default Inference","type":"RA","timestamp":"2015-12-03 12:48:38","scheme":"Default Inference","schemeID":"72"},{"nodeID":"115928","text":"Arguing","type":"YA","timestamp":"2015-12-03 12:48:38","scheme":"Arguing","schemeID":"80"}],"edges":[{"edgeID":"154553","fromID":"115901","toID":"34497","formEdgeID":null},{"edgeID":"154554","fromID":"34499","toID":"115901","formEdgeID":null},{"edgeID":"154555","fromID":"115902","toID":"34500","formEdgeID":null},{"edgeID":"154556","fromID":"34502","toID":"115902","formEdgeID":null},{"edgeID":"154557","fromID":"34499","toID":"115903","formEdgeID":null},{"edgeID":"154558","fromID":"115903","toID":"34502","formEdgeID":null},{"edgeID":"154559","fromID":"34502","toID":"115904","formEdgeID":null},{"edgeID":"154560","fromID":"115904","toID":"27416","formEdgeID":null},{"edgeID":"154561","fromID":"115904","toID":"115905","formEdgeID":null},{"edgeID":"154562","fromID":"115905","toID":"34497","formEdgeID":null},{"edgeID":"154563","fromID":"115906","toID":"34508","formEdgeID":null},{"edgeID":"154564","fromID":"34510","toID":"115906","formEdgeID":null},{"edgeID":"154565","fromID":"34502","toID":"115907","formEdgeID":null},{"edgeID":"154566","fromID":"115907","toID":"34510","formEdgeID":null},{"edgeID":"154567","fromID":"34508","toID":"115908","formEdgeID":null},{"edgeID":"154568","fromID":"115908","toID":"34500","formEdgeID":null},{"edgeID":"154569","fromID":"115907","toID":"115909","formEdgeID":null},{"edgeID":"154570","fromID":"115909","toID":"115908","formEdgeID":null},{"edgeID":"154571","fromID":"115910","toID":"34514","formEdgeID":null},{"edgeID":"154572","fromID":"34516","toID":"115910","formEdgeID":null},{"edgeID":"154573","fromID":"34508","toID":"115911","formEdgeID":null},{"edgeID":"154574","fromID":"115911","toID":"34514","formEdgeID":null},{"edgeID":"154575","fromID":"34510","toID":"115912","formEdgeID":null},{"edgeID":"154576","fromID":"115912","toID":"34516","formEdgeID":null},{"edgeID":"154577","fromID":"115912","toID":"115913","formEdgeID":null},{"edgeID":"154578","fromID":"115913","toID":"115911","formEdgeID":null},{"edgeID":"154579","fromID":"115914","toID":"34520","formEdgeID":null},{"edgeID":"154580","fromID":"34522","toID":"115914","formEdgeID":null},{"edgeID":"154581","fromID":"115915","toID":"34522","formEdgeID":null},{"edgeID":"154582","fromID":"34524","toID":"115915","formEdgeID":null},{"edgeID":"154583","fromID":"34516","toID":"115916","formEdgeID":null},{"edgeID":"154584","fromID":"115916","toID":"34524","formEdgeID":null},{"edgeID":"154585","fromID":"115917","toID":"34526","formEdgeID":null},{"edgeID":"154586","fromID":"34528","toID":"115917","formEdgeID":null},{"edgeID":"154587","fromID":"34524","toID":"115918","formEdgeID":null},{"edgeID":"154588","fromID":"115918","toID":"34528","formEdgeID":null},{"edgeID":"154589","fromID":"34526","toID":"115919","formEdgeID":null},{"edgeID":"154590","fromID":"115919","toID":"34520","formEdgeID":null},{"edgeID":"154591","fromID":"115918","toID":"115920","formEdgeID":null},{"edgeID":"154592","fromID":"115920","toID":"115919","formEdgeID":null},{"edgeID":"154593","fromID":"115921","toID":"34532","formEdgeID":null},{"edgeID":"154594","fromID":"34534","toID":"115921","formEdgeID":null},{"edgeID":"154595","fromID":"34516","toID":"115922","formEdgeID":null},{"edgeID":"154596","fromID":"115922","toID":"34534","formEdgeID":null},{"edgeID":"154597","fromID":"115923","toID":"34536","formEdgeID":null},{"edgeID":"154598","fromID":"34538","toID":"115923","formEdgeID":null},{"edgeID":"154599","fromID":"34534","toID":"115924","formEdgeID":null},{"edgeID":"154600","fromID":"115924","toID":"34538","formEdgeID":null},{"edgeID":"154601","fromID":"34536","toID":"115925","formEdgeID":null},{"edgeID":"154602","fromID":"115925","toID":"34532","formEdgeID":null},{"edgeID":"154603","fromID":"115924","toID":"115926","formEdgeID":null},{"edgeID":"154604","fromID":"115926","toID":"115925","formEdgeID":null},{"edgeID":"154605","fromID":"34500","toID":"115927","formEdgeID":null},{"edgeID":"154606","fromID":"115927","toID":"34497","formEdgeID":null},{"edgeID":"154607","fromID":"115903","toID":"115928","formEdgeID":null},{"edgeID":"154608","fromID":"115928","toID":"115927","formEdgeID":null}],"locutions":[{"nodeID":"27416","personID":"488","timestamp":"2014-02-28 14:38:41","start":null,"end":null,"source":null},{"nodeID":"34499","personID":"488","timestamp":"2014-08-12 12:44:49","start":null,"end":null,"source":null},{"nodeID":"34502","personID":"488","timestamp":"2014-08-12 12:44:49","start":null,"end":null,"source":null},{"nodeID":"34510","personID":"488","timestamp":"2014-08-12 12:44:49","start":null,"end":null,"source":null},{"nodeID":"34516","personID":"488","timestamp":"2014-08-12 12:44:49","start":null,"end":null,"source":null},{"nodeID":"34522","personID":"488","timestamp":"2014-08-12 12:44:49","start":null,"end":null,"source":null},{"nodeID":"34524","personID":"488","timestamp":"2014-08-12 12:44:49","start":null,"end":null,"source":null},{"nodeID":"34528","personID":"488","timestamp":"2014-08-12 12:44:49","start":null,"end":null,"source":null},{"nodeID":"34534","personID":"488","timestamp":"2014-08-12 12:44:49","start":null,"end":null,"source":null},{"nodeID":"34538","personID":"488","timestamp":"2014-08-12 12:44:49","start":null,"end":null,"source":null},{"nodeID":"34499","personID":"0","timestamp":"2015-12-03 12:48:40","start":null,"end":null,"source":null},{"nodeID":"34502","personID":"0","timestamp":"2015-12-03 12:48:40","start":null,"end":null,"source":null},{"nodeID":"27416","personID":"0","timestamp":"2015-12-03 12:48:40","start":null,"end":null,"source":null},{"nodeID":"34510","personID":"0","timestamp":"2015-12-03 12:48:40","start":null,"end":null,"source":null},{"nodeID":"34516","personID":"0","timestamp":"2015-12-03 12:48:40","start":null,"end":null,"source":null},{"nodeID":"34522","personID":"0","timestamp":"2015-12-03 12:48:40","start":null,"end":null,"source":null},{"nodeID":"34524","personID":"0","timestamp":"2015-12-03 12:48:40","start":null,"end":null,"source":null},{"nodeID":"34528","personID":"0","timestamp":"2015-12-03 12:48:40","start":null,"end":null,"source":null},{"nodeID":"34534","personID":"0","timestamp":"2015-12-03 12:48:40","start":null,"end":null,"source":null},{"nodeID":"34538","personID":"0","timestamp":"2015-12-03 12:48:40","start":null,"end":null,"source":null},{"nodeID":"27416","personID":"0","timestamp":"2015-12-04 10:35:12","start":null,"end":null,"source":null}]}