{"nodes":[{"nodeID":"42698","text":"Kenan used the word \u2018incentive\u2019","type":"I","timestamp":"2014-11-14 12:45:11"},{"nodeID":"42700","text":"Neil : Now you used the word \u2018incentive\u2019","type":"L","timestamp":"2014-11-14 12:45:11"},{"nodeID":"42701","text":"there are two different ways of improving the incentives to work","type":"I","timestamp":"2014-11-14 12:45:11"},{"nodeID":"42703","text":"Neil : and there are two different ways of improving the incentives to work","type":"L","timestamp":"2014-11-14 12:45:11"},{"nodeID":"42705","text":"One is to change the balance of or the generosity of out of work beneifts, maybe spend more on in work benefits like tax credits and so on","type":"I","timestamp":"2014-11-14 12:45:11"},{"nodeID":"42707","text":"Neil : One is to change the balance of or the generosity of out of work beneifts, maybe spend more on in work benefits like tax credits and so on","type":"L","timestamp":"2014-11-14 12:45:11"},{"nodeID":"42711","text":"we could turn our tax credits, which aren\u2019t really tax credits in the UK, into something you only get paid if you\u2019re working","type":"I","timestamp":"2014-11-14 12:45:11"},{"nodeID":"42713","text":"Neil : Maybe we could turn our tax credits, which aren\u2019t really tax credits in the UK, into something you only get paid if you\u2019re working","type":"L","timestamp":"2014-11-14 12:45:11"},{"nodeID":"42717","text":"that would be a good way of incentivising work","type":"I","timestamp":"2014-11-14 12:45:11"},{"nodeID":"42719","text":"Neil : that would be a good way of incentivising work","type":"L","timestamp":"2014-11-14 12:45:11"},{"nodeID":"42723","text":"we\u2019ve thought too much, funnily, about the financial incentives to work, and not enough about the conditionality in the system","type":"I","timestamp":"2014-11-14 12:45:11"},{"nodeID":"42725","text":"Neil : But we\u2019ve thought too much, funnily, about the financial incentives to work, and not enough about the conditionality in the system","type":"L","timestamp":"2014-11-14 12:45:12"},{"nodeID":"42729","text":"we ask people to do nothing in return for their benefits","type":"I","timestamp":"2014-11-14 12:45:12"},{"nodeID":"42731","text":"Neil : What do we ask people to do in return for their benefits?","type":"L","timestamp":"2014-11-14 12:45:12"},{"nodeID":"42735","text":"The idea of \u2018Work Fair\u2019, or of conditionality, is incredibly popular","type":"I","timestamp":"2014-11-14 12:45:12"},{"nodeID":"42737","text":"Neil : The idea of \u2018Work Fair\u2019, or of conditionality, is incredibly popular","type":"L","timestamp":"2014-11-14 12:45:12"},{"nodeID":"42741","text":"if you\u2019ve been on out of work benefits for more than a year, you should be asked to do community work in return for your benefits","type":"I","timestamp":"2014-11-14 12:45:12"},{"nodeID":"42743","text":"80% of people : if you\u2019ve been on out of work benefits for more than a year, you should be asked to do community work in return for your benefits","type":"L","timestamp":"2014-11-14 12:45:12"},{"nodeID":"42745","text":"Neil : 80% of people : if you\u2019ve been on out of work benefits for more than a year, you should be asked to do community work in return for your benefits","type":"L","timestamp":"2014-11-14 12:45:12"},{"nodeID":"42749","text":"they are right about that","type":"I","timestamp":"2014-11-14 12:45:12"},{"nodeID":"42751","text":"Neil : And they are right about that","type":"L","timestamp":"2014-11-14 12:45:12"},{"nodeID":"42755","text":"these programs from other countries, they work","type":"I","timestamp":"2014-11-14 12:45:12"},{"nodeID":"42757","text":"Neil : because we know that these programs from other countries, they work","type":"L","timestamp":"2014-11-14 12:45:12"},{"nodeID":"42761","text":"they really reduce unemployment","type":"I","timestamp":"2014-11-14 12:45:12"},{"nodeID":"42763","text":"Neil : they really reduce unemployment","type":"L","timestamp":"2014-11-14 12:45:12"},{"nodeID":"42767","text":"In one of the US states that went the furthest in this in diverting people from being on welfare, they managed at one point to reduce the number of people on benefits by 90%","type":"I","timestamp":"2014-11-14 12:45:12"},{"nodeID":"42769","text":"Neil : In one of the US states that went the furthest in this in diverting people from being on welfare, they managed at one point to reduce the number of people on benefits by 90%","type":"L","timestamp":"2014-11-14 12:45:12"},{"nodeID":"42773","text":"This is a huge opportunity that we\u2019ve barely begun to explore in the UK system","type":"I","timestamp":"2014-11-14 12:45:12"},{"nodeID":"42775","text":"Neil : This is a huge opportunity that we\u2019ve barely begun to explore in the UK system","type":"L","timestamp":"2014-11-14 12:45:13"},{"nodeID":"42781","text":"Kenan  : Except that when it reduces by 90%- what you meant is that they were all in low paid, part time jobs","type":"L","timestamp":"2014-11-14 12:45:13"},{"nodeID":"42785","text":"If that\u2019s the kind of job system that Neil wants, it seems to be a deeply immoral way of dealing with the quest of work, and how people should look at work","type":"I","timestamp":"2014-11-14 12:45:13"},{"nodeID":"42787","text":"Kenan  : If that\u2019s the kind of job system that you want, it seems to be a deeply immoral way of dealing with the quest of work, and how people should look at work","type":"L","timestamp":"2014-11-14 12:45:13"},{"nodeID":"117132","text":"Asserting","type":"YA","timestamp":"2015-12-04 12:12:43","scheme":"Asserting","schemeID":"74"},{"nodeID":"117133","text":"Asserting","type":"YA","timestamp":"2015-12-04 12:12:44","scheme":"Asserting","schemeID":"74"},{"nodeID":"117134","text":"TA","type":"TA","timestamp":"2015-12-04 12:12:44"},{"nodeID":"117135","text":"Asserting","type":"YA","timestamp":"2015-12-04 12:12:44","scheme":"Asserting","schemeID":"74"},{"nodeID":"117136","text":"Asserting","type":"YA","timestamp":"2015-12-04 12:12:44","scheme":"Asserting","schemeID":"74"},{"nodeID":"117137","text":"TA","type":"TA","timestamp":"2015-12-04 12:12:44"},{"nodeID":"117138","text":"Asserting","type":"YA","timestamp":"2015-12-04 12:12:44","scheme":"Asserting","schemeID":"74"},{"nodeID":"117139","text":"TA","type":"TA","timestamp":"2015-12-04 12:12:44"},{"nodeID":"117140","text":"Default Inference","type":"RA","timestamp":"2015-12-04 12:12:44","scheme":"Default Inference","schemeID":"72"},{"nodeID":"117141","text":"Arguing","type":"YA","timestamp":"2015-12-04 12:12:44","scheme":"Arguing","schemeID":"80"},{"nodeID":"117142","text":"Asserting","type":"YA","timestamp":"2015-12-04 12:12:44","scheme":"Asserting","schemeID":"74"},{"nodeID":"117143","text":"Rhetorical Questioning","type":"YA","timestamp":"2015-12-04 12:12:45","scheme":"RhetoricalQuestioning","schemeID":"85"},{"nodeID":"117144","text":"TA","type":"TA","timestamp":"2015-12-04 12:12:45"},{"nodeID":"117145","text":"Default Inference","type":"RA","timestamp":"2015-12-04 12:12:45","scheme":"Default Inference","schemeID":"72"},{"nodeID":"117146","text":"Arguing","type":"YA","timestamp":"2015-12-04 12:12:45","scheme":"Arguing","schemeID":"80"},{"nodeID":"117147","text":"Asserting","type":"YA","timestamp":"2015-12-04 12:12:45","scheme":"Asserting","schemeID":"74"},{"nodeID":"117148","text":"TA","type":"TA","timestamp":"2015-12-04 12:12:45"},{"nodeID":"117149","text":"Asserting","type":"YA","timestamp":"2015-12-04 12:12:45","scheme":"Asserting","schemeID":"74"},{"nodeID":"117150","text":"Asserting","type":"YA","timestamp":"2015-12-04 12:12:45","scheme":"Asserting","schemeID":"74"},{"nodeID":"117151","text":"TA","type":"TA","timestamp":"2015-12-04 12:12:45"},{"nodeID":"117152","text":"Default Inference","type":"RA","timestamp":"2015-12-04 12:12:45","scheme":"Default Inference","schemeID":"72"},{"nodeID":"117153","text":"Arguing","type":"YA","timestamp":"2015-12-04 12:12:46","scheme":"Arguing","schemeID":"80"},{"nodeID":"117154","text":"Asserting","type":"YA","timestamp":"2015-12-04 12:12:46","scheme":"Asserting","schemeID":"74"},{"nodeID":"117155","text":"TA","type":"TA","timestamp":"2015-12-04 12:12:46"},{"nodeID":"117156","text":"Popular Conceding","type":"YA","timestamp":"2015-12-04 12:12:46","scheme":"PopularConceding","schemeID":"88"},{"nodeID":"117157","text":"TA","type":"TA","timestamp":"2015-12-04 12:12:46"},{"nodeID":"117158","text":"Default Inference","type":"RA","timestamp":"2015-12-04 12:12:46","scheme":"Default Inference","schemeID":"72"},{"nodeID":"117159","text":"Arguing","type":"YA","timestamp":"2015-12-04 12:12:46","scheme":"Arguing","schemeID":"80"},{"nodeID":"117160","text":"Asserting","type":"YA","timestamp":"2015-12-04 12:12:46","scheme":"Asserting","schemeID":"74"},{"nodeID":"117161","text":"TA","type":"TA","timestamp":"2015-12-04 12:12:46"},{"nodeID":"117162","text":"Default Inference","type":"RA","timestamp":"2015-12-04 12:12:46","scheme":"Default Inference","schemeID":"72"},{"nodeID":"117163","text":"Arguing","type":"YA","timestamp":"2015-12-04 12:12:46","scheme":"Arguing","schemeID":"80"},{"nodeID":"117164","text":"Asserting","type":"YA","timestamp":"2015-12-04 12:12:47","scheme":"Asserting","schemeID":"74"},{"nodeID":"117165","text":"TA","type":"TA","timestamp":"2015-12-04 12:12:47"},{"nodeID":"117166","text":"Example","type":"RA","timestamp":"2015-12-04 12:12:47","scheme":"Example","schemeID":"14"},{"nodeID":"117167","text":"Arguing","type":"YA","timestamp":"2015-12-04 12:12:47","scheme":"Arguing","schemeID":"80"},{"nodeID":"117168","text":"Asserting","type":"YA","timestamp":"2015-12-04 12:12:47","scheme":"Asserting","schemeID":"74"},{"nodeID":"117169","text":"when it reduces by 90%- what Neil meant is that they were all in low paid, part time jobs","type":"I","timestamp":"2015-12-04 12:12:47"},{"nodeID":"117170","text":"Asserting","type":"YA","timestamp":"2015-12-04 12:12:47","scheme":"Asserting","schemeID":"74"},{"nodeID":"117171","text":"Asserting","type":"YA","timestamp":"2015-12-04 12:12:47","scheme":"Asserting","schemeID":"74"},{"nodeID":"117172","text":"TA","type":"TA","timestamp":"2015-12-04 12:12:47"},{"nodeID":"117173","text":"Default Inference","type":"RA","timestamp":"2015-12-04 12:12:47","scheme":"Default Inference","schemeID":"72"},{"nodeID":"117174","text":"Arguing","type":"YA","timestamp":"2015-12-04 12:12:47","scheme":"Arguing","schemeID":"80"},{"nodeID":"117175","text":"Default Inference","type":"RA","timestamp":"2015-12-04 12:12:47","scheme":"Default Inference","schemeID":"72"},{"nodeID":"117176","text":"Arguing","type":"YA","timestamp":"2015-12-04 12:12:48","scheme":"Arguing","schemeID":"80"},{"nodeID":"117177","text":"Default Transition","type":"TA","timestamp":"2015-12-04 12:12:48","scheme":"Default Transition","schemeID":"82"},{"nodeID":"117178","text":"Default Inference","type":"RA","timestamp":"2015-12-04 12:12:48","scheme":"Default Inference","schemeID":"72"},{"nodeID":"117179","text":"Arguing","type":"YA","timestamp":"2015-12-04 12:12:48","scheme":"Arguing","schemeID":"80"},{"nodeID":"117180","text":"Default Transition","type":"TA","timestamp":"2015-12-04 12:12:48","scheme":"Default Transition","schemeID":"82"},{"nodeID":"117181","text":"Agreeing","type":"YA","timestamp":"2015-12-04 12:12:48","scheme":"Agreeing","schemeID":"77"},{"nodeID":"117182","text":"Default Transition","type":"TA","timestamp":"2015-12-04 12:12:48","scheme":"Default Transition","schemeID":"82"},{"nodeID":"117183","text":"Default Transition","type":"TA","timestamp":"2015-12-04 12:12:48","scheme":"Default Transition","schemeID":"82"},{"nodeID":"117184","text":"Default Conflict","type":"CA","timestamp":"2015-12-04 12:12:48","scheme":"Default Conflict","schemeID":"71"},{"nodeID":"117185","text":"Disagreeing","type":"YA","timestamp":"2015-12-04 12:12:48","scheme":"Disagreeing","schemeID":"78"}],"edges":[{"edgeID":"156531","fromID":"117132","toID":"42698","formEdgeID":null},{"edgeID":"156532","fromID":"42700","toID":"117132","formEdgeID":null},{"edgeID":"156533","fromID":"117133","toID":"42701","formEdgeID":null},{"edgeID":"156534","fromID":"42703","toID":"117133","formEdgeID":null},{"edgeID":"156535","fromID":"42700","toID":"117134","formEdgeID":null},{"edgeID":"156536","fromID":"117134","toID":"42703","formEdgeID":null},{"edgeID":"156537","fromID":"117135","toID":"42705","formEdgeID":null},{"edgeID":"156538","fromID":"42707","toID":"117135","formEdgeID":null},{"edgeID":"156539","fromID":"117136","toID":"42711","formEdgeID":null},{"edgeID":"156540","fromID":"42713","toID":"117136","formEdgeID":null},{"edgeID":"156541","fromID":"42707","toID":"117137","formEdgeID":null},{"edgeID":"156542","fromID":"117137","toID":"42713","formEdgeID":null},{"edgeID":"156543","fromID":"117138","toID":"42717","formEdgeID":null},{"edgeID":"156544","fromID":"42719","toID":"117138","formEdgeID":null},{"edgeID":"156545","fromID":"42713","toID":"117139","formEdgeID":null},{"edgeID":"156546","fromID":"117139","toID":"42719","formEdgeID":null},{"edgeID":"156547","fromID":"42717","toID":"117140","formEdgeID":null},{"edgeID":"156548","fromID":"117140","toID":"42711","formEdgeID":null},{"edgeID":"156549","fromID":"117139","toID":"117141","formEdgeID":null},{"edgeID":"156550","fromID":"117141","toID":"117140","formEdgeID":null},{"edgeID":"156551","fromID":"117142","toID":"42723","formEdgeID":null},{"edgeID":"156552","fromID":"42725","toID":"117142","formEdgeID":null},{"edgeID":"156553","fromID":"117143","toID":"42729","formEdgeID":null},{"edgeID":"156554","fromID":"42731","toID":"117143","formEdgeID":null},{"edgeID":"156555","fromID":"42725","toID":"117144","formEdgeID":null},{"edgeID":"156556","fromID":"117144","toID":"42731","formEdgeID":null},{"edgeID":"156557","fromID":"42723","toID":"117145","formEdgeID":null},{"edgeID":"156558","fromID":"117145","toID":"42729","formEdgeID":null},{"edgeID":"156559","fromID":"117144","toID":"117146","formEdgeID":null},{"edgeID":"156560","fromID":"117146","toID":"117145","formEdgeID":null},{"edgeID":"156561","fromID":"117147","toID":"42735","formEdgeID":null},{"edgeID":"156562","fromID":"42737","toID":"117147","formEdgeID":null},{"edgeID":"156563","fromID":"42731","toID":"117148","formEdgeID":null},{"edgeID":"156564","fromID":"117148","toID":"42737","formEdgeID":null},{"edgeID":"156565","fromID":"117149","toID":"42741","formEdgeID":null},{"edgeID":"156566","fromID":"42743","toID":"117149","formEdgeID":null},{"edgeID":"156567","fromID":"117150","toID":"42743","formEdgeID":null},{"edgeID":"156568","fromID":"42745","toID":"117150","formEdgeID":null},{"edgeID":"156569","fromID":"42737","toID":"117151","formEdgeID":null},{"edgeID":"156570","fromID":"117151","toID":"42745","formEdgeID":null},{"edgeID":"156571","fromID":"42735","toID":"117152","formEdgeID":null},{"edgeID":"156572","fromID":"117152","toID":"42743","formEdgeID":null},{"edgeID":"156573","fromID":"117151","toID":"117153","formEdgeID":null},{"edgeID":"156574","fromID":"117153","toID":"117152","formEdgeID":null},{"edgeID":"156575","fromID":"117154","toID":"42749","formEdgeID":null},{"edgeID":"156576","fromID":"42751","toID":"117154","formEdgeID":null},{"edgeID":"156577","fromID":"42745","toID":"117155","formEdgeID":null},{"edgeID":"156578","fromID":"117155","toID":"42751","formEdgeID":null},{"edgeID":"156579","fromID":"117156","toID":"42755","formEdgeID":null},{"edgeID":"156580","fromID":"42757","toID":"117156","formEdgeID":null},{"edgeID":"156581","fromID":"42751","toID":"117157","formEdgeID":null},{"edgeID":"156582","fromID":"117157","toID":"42757","formEdgeID":null},{"edgeID":"156583","fromID":"42755","toID":"117158","formEdgeID":null},{"edgeID":"156584","fromID":"117158","toID":"42749","formEdgeID":null},{"edgeID":"156585","fromID":"117157","toID":"117159","formEdgeID":null},{"edgeID":"156586","fromID":"117159","toID":"117158","formEdgeID":null},{"edgeID":"156587","fromID":"117160","toID":"42761","formEdgeID":null},{"edgeID":"156588","fromID":"42763","toID":"117160","formEdgeID":null},{"edgeID":"156589","fromID":"42757","toID":"117161","formEdgeID":null},{"edgeID":"156590","fromID":"117161","toID":"42763","formEdgeID":null},{"edgeID":"156591","fromID":"42761","toID":"117162","formEdgeID":null},{"edgeID":"156592","fromID":"117162","toID":"42755","formEdgeID":null},{"edgeID":"156593","fromID":"117161","toID":"117163","formEdgeID":null},{"edgeID":"156594","fromID":"117163","toID":"117162","formEdgeID":null},{"edgeID":"156595","fromID":"117164","toID":"42767","formEdgeID":null},{"edgeID":"156596","fromID":"42769","toID":"117164","formEdgeID":null},{"edgeID":"156597","fromID":"42763","toID":"117165","formEdgeID":null},{"edgeID":"156598","fromID":"117165","toID":"42769","formEdgeID":null},{"edgeID":"156599","fromID":"42767","toID":"117166","formEdgeID":null},{"edgeID":"156600","fromID":"117166","toID":"42761","formEdgeID":null},{"edgeID":"156601","fromID":"117165","toID":"117167","formEdgeID":null},{"edgeID":"156602","fromID":"117167","toID":"117166","formEdgeID":null},{"edgeID":"156603","fromID":"117168","toID":"42773","formEdgeID":null},{"edgeID":"156604","fromID":"42775","toID":"117168","formEdgeID":null},{"edgeID":"156605","fromID":"117170","toID":"117169","formEdgeID":null},{"edgeID":"156606","fromID":"42781","toID":"117170","formEdgeID":null},{"edgeID":"156607","fromID":"117171","toID":"42785","formEdgeID":null},{"edgeID":"156608","fromID":"42787","toID":"117171","formEdgeID":null},{"edgeID":"156609","fromID":"42781","toID":"117172","formEdgeID":null},{"edgeID":"156610","fromID":"117172","toID":"42787","formEdgeID":null},{"edgeID":"156611","fromID":"117169","toID":"117173","formEdgeID":null},{"edgeID":"156612","fromID":"117173","toID":"42785","formEdgeID":null},{"edgeID":"156613","fromID":"117172","toID":"117174","formEdgeID":null},{"edgeID":"156614","fromID":"117174","toID":"117173","formEdgeID":null},{"edgeID":"156615","fromID":"42705","toID":"117175","formEdgeID":null},{"edgeID":"156616","fromID":"117175","toID":"42711","formEdgeID":null},{"edgeID":"156617","fromID":"117137","toID":"117176","formEdgeID":null},{"edgeID":"156618","fromID":"117176","toID":"117175","formEdgeID":null},{"edgeID":"156619","fromID":"42703","toID":"117177","formEdgeID":null},{"edgeID":"156620","fromID":"117177","toID":"42707","formEdgeID":null},{"edgeID":"156621","fromID":"42705","toID":"117178","formEdgeID":null},{"edgeID":"156622","fromID":"117178","toID":"42701","formEdgeID":null},{"edgeID":"156623","fromID":"117177","toID":"117179","formEdgeID":null},{"edgeID":"156624","fromID":"117179","toID":"117178","formEdgeID":null},{"edgeID":"156625","fromID":"42719","toID":"117180","formEdgeID":null},{"edgeID":"156626","fromID":"117180","toID":"42725","formEdgeID":null},{"edgeID":"156627","fromID":"117155","toID":"117181","formEdgeID":null},{"edgeID":"156628","fromID":"117181","toID":"42741","formEdgeID":null},{"edgeID":"156629","fromID":"42745","toID":"117182","formEdgeID":null},{"edgeID":"156630","fromID":"117182","toID":"42775","formEdgeID":null},{"edgeID":"156631","fromID":"42775","toID":"117183","formEdgeID":null},{"edgeID":"156632","fromID":"117183","toID":"42781","formEdgeID":null},{"edgeID":"156633","fromID":"117169","toID":"117184","formEdgeID":null},{"edgeID":"156634","fromID":"117184","toID":"42773","formEdgeID":null},{"edgeID":"156635","fromID":"117183","toID":"117185","formEdgeID":null},{"edgeID":"156636","fromID":"117185","toID":"117184","formEdgeID":null}],"locutions":[{"nodeID":"42700","personID":"592","timestamp":"2014-11-14 12:45:14","start":null,"end":null,"source":null},{"nodeID":"42703","personID":"592","timestamp":"2014-11-14 12:45:14","start":null,"end":null,"source":null},{"nodeID":"42707","personID":"592","timestamp":"2014-11-14 12:45:14","start":null,"end":null,"source":null},{"nodeID":"42713","personID":"592","timestamp":"2014-11-14 12:45:14","start":null,"end":null,"source":null},{"nodeID":"42719","personID":"592","timestamp":"2014-11-14 12:45:14","start":null,"end":null,"source":null},{"nodeID":"42725","personID":"592","timestamp":"2014-11-14 12:45:14","start":null,"end":null,"source":null},{"nodeID":"42731","personID":"592","timestamp":"2014-11-14 12:45:14","start":null,"end":null,"source":null},{"nodeID":"42737","personID":"592","timestamp":"2014-11-14 12:45:14","start":null,"end":null,"source":null},{"nodeID":"42743","personID":"593","timestamp":"2014-11-14 12:45:14","start":null,"end":null,"source":null},{"nodeID":"42745","personID":"592","timestamp":"2014-11-14 12:45:14","start":null,"end":null,"source":null},{"nodeID":"42751","personID":"592","timestamp":"2014-11-14 12:45:14","start":null,"end":null,"source":null},{"nodeID":"42757","personID":"592","timestamp":"2014-11-14 12:45:14","start":null,"end":null,"source":null},{"nodeID":"42763","personID":"592","timestamp":"2014-11-14 12:45:14","start":null,"end":null,"source":null},{"nodeID":"42769","personID":"592","timestamp":"2014-11-14 12:45:14","start":null,"end":null,"source":null},{"nodeID":"42775","personID":"592","timestamp":"2014-11-14 12:45:14","start":null,"end":null,"source":null},{"nodeID":"42781","personID":"512","timestamp":"2014-11-14 12:45:14","start":null,"end":null,"source":null},{"nodeID":"42787","personID":"512","timestamp":"2014-11-14 12:45:14","start":null,"end":null,"source":null},{"nodeID":"42700","personID":"1295","timestamp":"2015-12-04 12:12:51","start":null,"end":null,"source":null},{"nodeID":"42703","personID":"1295","timestamp":"2015-12-04 12:12:51","start":null,"end":null,"source":null},{"nodeID":"42707","personID":"1295","timestamp":"2015-12-04 12:12:51","start":null,"end":null,"source":null},{"nodeID":"42713","personID":"1295","timestamp":"2015-12-04 12:12:51","start":null,"end":null,"source":null},{"nodeID":"42719","personID":"1295","timestamp":"2015-12-04 12:12:51","start":null,"end":null,"source":null},{"nodeID":"42725","personID":"1295","timestamp":"2015-12-04 12:12:51","start":null,"end":null,"source":null},{"nodeID":"42731","personID":"1295","timestamp":"2015-12-04 12:12:51","start":null,"end":null,"source":null},{"nodeID":"42737","personID":"1295","timestamp":"2015-12-04 12:12:51","start":null,"end":null,"source":null},{"nodeID":"42743","personID":"593","timestamp":"2015-12-04 12:12:51","start":null,"end":null,"source":null},{"nodeID":"42745","personID":"1295","timestamp":"2015-12-04 12:12:51","start":null,"end":null,"source":null},{"nodeID":"42751","personID":"1295","timestamp":"2015-12-04 12:12:51","start":null,"end":null,"source":null},{"nodeID":"42757","personID":"1295","timestamp":"2015-12-04 12:12:51","start":null,"end":null,"source":null},{"nodeID":"42763","personID":"1295","timestamp":"2015-12-04 12:12:51","start":null,"end":null,"source":null},{"nodeID":"42769","personID":"1295","timestamp":"2015-12-04 12:12:51","start":null,"end":null,"source":null},{"nodeID":"42775","personID":"1295","timestamp":"2015-12-04 12:12:51","start":null,"end":null,"source":null},{"nodeID":"42781","personID":"512","timestamp":"2015-12-04 12:12:51","start":null,"end":null,"source":null},{"nodeID":"42787","personID":"512","timestamp":"2015-12-04 12:12:51","start":null,"end":null,"source":null}]}