{"nodes":[{"nodeID":"268943","text":"student panel thinks X of what they heard","type":"I","timestamp":"2017-03-31 10:55:43"},{"nodeID":"268946","text":"Michael : Howard Davies, thank you very much indeed.\u00a0","type":"L","timestamp":"2017-03-31 10:55:43"},{"nodeID":"268947","text":"Anon: Michael : Howard Davies, thank you very much indeed.\u00a0","type":"L","timestamp":"2017-03-31 10:55:43"},{"nodeID":"268949","text":"Michael : So, student panel, what do you think of what you heard?","type":"L","timestamp":"2017-03-31 10:55:44"},{"nodeID":"268950","text":"Anon: Michael : So, student panel, what do you think of what you heard?","type":"L","timestamp":"2017-03-31 10:55:44"},{"nodeID":"268953","text":"Shiv Malik: his generation, or the younger generation were serfs.","type":"L","timestamp":"2017-03-31 10:55:44"},{"nodeID":"268954","text":"Anon: Michael : Jane. Shiv Malik, our first witness, I think he said that his generation, or the younger generation were serfs.","type":"L","timestamp":"2017-03-31 10:55:44"},{"nodeID":"268956","text":"Michael : Jane. Shiv Malik, our first witness, I think he said that his generation, or the younger generation were serfs.","type":"L","timestamp":"2017-03-31 10:55:45"},{"nodeID":"268957","text":"Anon: Michael : Michael : Jane. Shiv Malik, our first witness, I think he said that his generation, or the younger generation were serfs.","type":"L","timestamp":"2017-03-31 10:55:45"},{"nodeID":"268959","text":"Michael : Do you feel a trainee serf?","type":"L","timestamp":"2017-03-31 10:55:45"},{"nodeID":"268960","text":"Anon: Michael : Do you feel a trainee serf?","type":"L","timestamp":"2017-03-31 10:55:45"},{"nodeID":"268964","text":"I'm not so obsessed with having a house that I want to build on the green belt,","type":"I","timestamp":"2017-03-31 10:55:46"},{"nodeID":"268966","text":"you've overlooked the fact that young people aren't all obsessed with having a house.","type":"I","timestamp":"2017-03-31 10:55:46"},{"nodeID":"268967","text":"Jane : Well, I'm gonna be honest. I don't agree with you,","type":"L","timestamp":"2017-03-31 10:55:46"},{"nodeID":"268968","text":"Anon: Jane : Well, I'm gonna be honest. I don't agree with you,","type":"L","timestamp":"2017-03-31 10:55:46"},{"nodeID":"268970","text":"Jane : I'm part of the younger generation","type":"L","timestamp":"2017-03-31 10:55:46"},{"nodeID":"268971","text":"Anon: Jane : I'm part of the younger generation","type":"L","timestamp":"2017-03-31 10:55:46"},{"nodeID":"268973","text":"Jane : I'm not so obsessed with having a house that I want to build on the green belt,","type":"L","timestamp":"2017-03-31 10:55:47"},{"nodeID":"268974","text":"Anon: Jane : I'm not so obsessed with having a house that I want to build on the green belt,","type":"L","timestamp":"2017-03-31 10:55:47"},{"nodeID":"268976","text":"Jane : I think that you've overlooked that a little,","type":"L","timestamp":"2017-03-31 10:55:47"},{"nodeID":"268977","text":"Anon: Jane : I think that you've overlooked that a little,","type":"L","timestamp":"2017-03-31 10:55:47"},{"nodeID":"268979","text":"Jane : you've overlooked the fact that young people aren't all obsessed with having a house.","type":"L","timestamp":"2017-03-31 10:55:47"},{"nodeID":"268980","text":"Anon: Jane : you've overlooked the fact that young people aren't all obsessed with having a house.","type":"L","timestamp":"2017-03-31 10:55:47"},{"nodeID":"268993","text":"perhaps we ought to settle for less","type":"I","timestamp":"2017-03-31 10:55:49"},{"nodeID":"268996","text":"Maddie: perhaps we ought to settle for less","type":"L","timestamp":"2017-03-31 10:55:49"},{"nodeID":"268997","text":"Anon: Michael : And Maddie, was it you that said \"perhaps we ought to settle for less\",","type":"L","timestamp":"2017-03-31 10:55:50"},{"nodeID":"268999","text":"Michael : you the sort of person who would settle for less?","type":"L","timestamp":"2017-03-31 10:55:50"},{"nodeID":"269000","text":"Anon: Michael : you the sort of person who would settle for less?","type":"L","timestamp":"2017-03-31 10:55:50"},{"nodeID":"269002","text":"Michael : And Maddie, was it you that said \"perhaps we ought to settle for less\",","type":"L","timestamp":"2017-03-31 10:55:50"},{"nodeID":"269003","text":"Anon: Michael : Michael : And Maddie, was it you that said \"perhaps we ought to settle for less\",","type":"L","timestamp":"2017-03-31 10:55:50"},{"nodeID":"269006","text":"when it comes down to it, I - don't shake your head, Poppy.","type":"I","timestamp":"2017-03-31 10:55:51"},{"nodeID":"269009","text":"even in this room today, all of the talk of development has been about environmentally friendly development, and it shows a lot about the values in this very room, and about how much nature means to every single one of us.","type":"I","timestamp":"2017-03-31 10:55:51"},{"nodeID":"269010","text":"We can completely see how much nature means to us just by this conversation.","type":"I","timestamp":"2017-03-31 10:55:51"},{"nodeID":"269012","text":"Maddie : Well, I mean when it comes down to it, I - don't shake your head, Poppy.","type":"L","timestamp":"2017-03-31 10:55:51"},{"nodeID":"269013","text":"Anon: Maddie : Well, I mean when it comes down to it, I - don't shake your head, Poppy.","type":"L","timestamp":"2017-03-31 10:55:51"},{"nodeID":"269015","text":"Maddie : When it comes down to it, I think my generation are the ones who have been educated the most about this topic.","type":"L","timestamp":"2017-03-31 10:55:52"},{"nodeID":"269016","text":"Anon: Maddie : When it comes down to it, I think my generation are the ones who have been educated the most about this topic.","type":"L","timestamp":"2017-03-31 10:55:52"},{"nodeID":"269018","text":"Maddie : I think it really comes out when you have arguments like this.","type":"L","timestamp":"2017-03-31 10:55:52"},{"nodeID":"269019","text":"Anon: Maddie : I think it really comes out when you have arguments like this.","type":"L","timestamp":"2017-03-31 10:55:52"},{"nodeID":"269021","text":"Maddie : even in this room today, all of the talk of development has been about environmentally friendly development, and it shows a lot about the values in this very room, and about how much nature means to every single one of us.","type":"L","timestamp":"2017-03-31 10:55:52"},{"nodeID":"269022","text":"Anon: Maddie : even in this room today, all of the talk of development has been about environmentally friendly development, and it shows a lot about the values in this very room, and about how much nature means to every single one of us.","type":"L","timestamp":"2017-03-31 10:55:53"},{"nodeID":"269024","text":"Maddie : We can completely see how much nature means to us just by this conversation.","type":"L","timestamp":"2017-03-31 10:55:53"},{"nodeID":"269025","text":"Anon: Maddie : We can completely see how much nature means to us just by this conversation.","type":"L","timestamp":"2017-03-31 10:55:53"},{"nodeID":"269038","text":"if maybe your own family own their own home, but you won't own your own home. Maddie will\/won't feel unfairly cheated or generationally abused","type":"I","timestamp":"2017-03-31 10:55:55"},{"nodeID":"269040","text":"Michael : And if the end result is ... I don't know, I mean ... maybe your own family own their own home, but you won't own your own home. You won't feel unfairly cheated or generationally abused?","type":"L","timestamp":"2017-03-31 10:55:55"},{"nodeID":"269041","text":"Anon: Michael : And if the end result is ... I don't know, I mean ... maybe your own family own their own home, but you won't own your own home. You won't feel unfairly cheated or generationally abused?","type":"L","timestamp":"2017-03-31 10:55:55"},{"nodeID":"269043","text":"Well, my mother rents and my father owns","type":"I","timestamp":"2017-03-31 10:55:55"},{"nodeID":"269048","text":"Maddie : Well, my mother rents and my father owns","type":"L","timestamp":"2017-03-31 10:55:56"},{"nodeID":"269049","text":"Anon: Maddie : Well, my mother rents and my father owns","type":"L","timestamp":"2017-03-31 10:55:56"},{"nodeID":"269051","text":"Maddie : I can see both sides of it","type":"L","timestamp":"2017-03-31 10:55:56"},{"nodeID":"269052","text":"Anon: Maddie : I can see both sides of it","type":"L","timestamp":"2017-03-31 10:55:56"},{"nodeID":"269054","text":"Maddie : I think we all accept the realities of what we have to live with, and we'll all deal with it.","type":"L","timestamp":"2017-03-31 10:55:57"},{"nodeID":"269055","text":"Anon: Maddie : I think we all accept the realities of what we have to live with, and we'll all deal with it.","type":"L","timestamp":"2017-03-31 10:55:57"},{"nodeID":"269057","text":"Maddie : I don't think either way my quality of life is going to dramatically drop down the drain. I think I'll be fine, thanks.","type":"L","timestamp":"2017-03-31 10:55:57"},{"nodeID":"269058","text":"Anon: Maddie : I don't think either way my quality of life is going to dramatically drop down the drain. I think I'll be fine, thanks.","type":"L","timestamp":"2017-03-31 10:55:57"},{"nodeID":"269070","text":"Michael : Poppy, you were shaking your head. Will you be fine?","type":"L","timestamp":"2017-03-31 10:55:58"},{"nodeID":"269071","text":"Anon: Michael : Poppy, you were shaking your head. Will you be fine?","type":"L","timestamp":"2017-03-31 10:55:59"},{"nodeID":"269073","text":"Poppy : I disagree, I-","type":"L","timestamp":"2017-03-31 10:55:59"},{"nodeID":"269074","text":"Anon: Poppy : I disagree, I-","type":"L","timestamp":"2017-03-31 10:55:59"},{"nodeID":"269079","text":"Michael : Or resentful?","type":"L","timestamp":"2017-03-31 10:56:00"},{"nodeID":"269080","text":"Anon: Michael : Or resentful?","type":"L","timestamp":"2017-03-31 10:56:00"},{"nodeID":"269083","text":"the young generation don't care about owning a home","type":"I","timestamp":"2017-03-31 10:56:00"},{"nodeID":"269085","text":"With such an arbitrary piece of policy such as green belt land, it's not fair - especially on younger generations -","type":"I","timestamp":"2017-03-31 10:56:00"},{"nodeID":"269086","text":"it's not fair on anybody that wants to live in an area that's heavily populated or very popular.","type":"I","timestamp":"2017-03-31 10:56:00"},{"nodeID":"269089","text":"Poppy : \tI place a great importance on the prospect of owning a home in a city that I want to work in and that I want to live in for a lengthy period of time.","type":"L","timestamp":"2017-03-31 10:56:01"},{"nodeID":"269090","text":"Anon: Poppy : \tI place a great importance on the prospect of owning a home in a city that I want to work in and that I want to live in for a lengthy period of time.","type":"L","timestamp":"2017-03-31 10:56:01"},{"nodeID":"269093","text":"Jane: the young generation don't care about owning a home","type":"L","timestamp":"2017-03-31 10:56:01"},{"nodeID":"269094","text":"Anon: Poppy :  I disagree with Jane's point that the young generation don't care about owning a home,","type":"L","timestamp":"2017-03-31 10:56:01"},{"nodeID":"269096","text":"Poppy :  I disagree with Jane's point that the young generation don't care about owning a home,","type":"L","timestamp":"2017-03-31 10:56:02"},{"nodeID":"269097","text":"Anon: Poppy : Poppy :  I disagree with Jane's point that the young generation don't care about owning a home,","type":"L","timestamp":"2017-03-31 10:56:02"},{"nodeID":"269100","text":"Poppy : owning a home and having that security in your life is of great importance to me.","type":"L","timestamp":"2017-03-31 10:56:02"},{"nodeID":"269101","text":"Anon: Poppy : owning a home and having that security in your life is of great importance to me.","type":"L","timestamp":"2017-03-31 10:56:02"},{"nodeID":"269106","text":"Poppy : With such an arbitrary piece of policy such as green belt land, it's not fair - especially on younger generations -","type":"L","timestamp":"2017-03-31 10:56:03"},{"nodeID":"269107","text":"Anon: Poppy : With such an arbitrary piece of policy such as green belt land, it's not fair - especially on younger generations -","type":"L","timestamp":"2017-03-31 10:56:03"},{"nodeID":"269110","text":"Poppy :  it's not fair on anybody that wants to live in an area that's heavily populated or very popular.","type":"L","timestamp":"2017-03-31 10:56:03"},{"nodeID":"269111","text":"Anon: Poppy :  it's not fair on anybody that wants to live in an area that's heavily populated or very popular.","type":"L","timestamp":"2017-03-31 10:56:03"},{"nodeID":"269113","text":"Poppy : I don't see the problem with urban sprawl.","type":"L","timestamp":"2017-03-31 10:56:04"},{"nodeID":"269114","text":"Anon: Poppy : I don't see the problem with urban sprawl.","type":"L","timestamp":"2017-03-31 10:56:04"},{"nodeID":"270590","text":"Shiv Malik's generation, or the younger generation were serfs.","type":"I","timestamp":"2017-03-31 13:26:52"},{"nodeID":"270591","text":"Jane Fidge does\/does not feel a trainee serf","type":"I","timestamp":"2017-03-31 13:26:52"},{"nodeID":"270592","text":"Pure Questioning","type":"YA","timestamp":"2017-03-31 13:26:52","scheme":"PureQuestioning","schemeID":"91"},{"nodeID":"270593","text":"Default Transition","type":"TA","timestamp":"2017-03-31 13:26:52","scheme":"Default Transition","schemeID":"82"},{"nodeID":"270594","text":"Asserting","type":"YA","timestamp":"2017-03-31 13:26:52","scheme":"Asserting","schemeID":"74"},{"nodeID":"270595","text":"Asserting","type":"YA","timestamp":"2017-03-31 13:26:53","scheme":"Asserting","schemeID":"74"},{"nodeID":"270596","text":"Assertive Questioning","type":"YA","timestamp":"2017-03-31 13:26:53","scheme":"AssertiveQuestioning","schemeID":"73"},{"nodeID":"270597","text":"Default Transition","type":"TA","timestamp":"2017-03-31 13:26:54","scheme":"Default Transition","schemeID":"82"},{"nodeID":"270598","text":"Default Transition","type":"TA","timestamp":"2017-03-31 13:26:54","scheme":"Default Transition","schemeID":"82"},{"nodeID":"270599","text":"Jane Fidge is part of the younger generation","type":"I","timestamp":"2017-03-31 13:26:54"},{"nodeID":"270600","text":"you've overlooked that a little,","type":"I","timestamp":"2017-03-31 13:26:54"},{"nodeID":"270601","text":"Asserting","type":"YA","timestamp":"2017-03-31 13:26:54","scheme":"Asserting","schemeID":"74"},{"nodeID":"270602","text":"Asserting","type":"YA","timestamp":"2017-03-31 13:26:55","scheme":"Asserting","schemeID":"74"},{"nodeID":"270603","text":"Asserting","type":"YA","timestamp":"2017-03-31 13:26:56","scheme":"Asserting","schemeID":"74"},{"nodeID":"270604","text":"Asserting","type":"YA","timestamp":"2017-03-31 13:26:56","scheme":"Asserting","schemeID":"74"},{"nodeID":"270605","text":"Default Transition","type":"TA","timestamp":"2017-03-31 13:26:57","scheme":"Default Transition","schemeID":"82"},{"nodeID":"270606","text":"Disagreeing","type":"YA","timestamp":"2017-03-31 13:26:57","scheme":"Disagreeing","schemeID":"78"},{"nodeID":"270607","text":"Default Transition","type":"TA","timestamp":"2017-03-31 13:26:57","scheme":"Default Transition","schemeID":"82"},{"nodeID":"270608","text":"Default Conflict","type":"CA","timestamp":"2017-03-31 13:26:57","scheme":"Default Conflict","schemeID":"71"},{"nodeID":"270609","text":"Disagreeing","type":"YA","timestamp":"2017-03-31 13:26:57","scheme":"Disagreeing","schemeID":"78"},{"nodeID":"270610","text":"Default Transition","type":"TA","timestamp":"2017-03-31 13:26:57","scheme":"Default Transition","schemeID":"82"},{"nodeID":"270611","text":"Default Transition","type":"TA","timestamp":"2017-03-31 13:26:57","scheme":"Default Transition","schemeID":"82"},{"nodeID":"270612","text":"Default Inference","type":"RA","timestamp":"2017-03-31 13:26:58","scheme":"Default Inference","schemeID":"72"},{"nodeID":"270613","text":"Default Inference","type":"RA","timestamp":"2017-03-31 13:26:58","scheme":"Default Inference","schemeID":"72"},{"nodeID":"270614","text":"Default Transition","type":"TA","timestamp":"2017-03-31 13:26:58","scheme":"Default Transition","schemeID":"82"},{"nodeID":"270615","text":"Arguing","type":"YA","timestamp":"2017-03-31 13:26:58","scheme":"Arguing","schemeID":"80"},{"nodeID":"270616","text":"Arguing","type":"YA","timestamp":"2017-03-31 13:26:58","scheme":"Arguing","schemeID":"80"},{"nodeID":"270617","text":"Maddie is \/ is not the sort of person who would settle for less","type":"I","timestamp":"2017-03-31 13:26:59"},{"nodeID":"270618","text":"Asserting","type":"YA","timestamp":"2017-03-31 13:26:59","scheme":"Asserting","schemeID":"74"},{"nodeID":"270619","text":"Pure Questioning","type":"YA","timestamp":"2017-03-31 13:26:59","scheme":"PureQuestioning","schemeID":"91"},{"nodeID":"270620","text":"Rhetorical Questioning","type":"YA","timestamp":"2017-03-31 13:26:59","scheme":"RhetoricalQuestioning","schemeID":"85"},{"nodeID":"270621","text":"Default Transition","type":"TA","timestamp":"2017-03-31 13:27:00","scheme":"Default Transition","schemeID":"82"},{"nodeID":"270622","text":"Default Transition","type":"TA","timestamp":"2017-03-31 13:27:00","scheme":"Default Transition","schemeID":"82"},{"nodeID":"270623","text":"When it comes down to it, Maddie Groeger-Wilson's generation are the ones who have been educated the most about this topic.","type":"I","timestamp":"2017-03-31 13:27:00"},{"nodeID":"270624","text":"it really comes out when you have arguments like this.","type":"I","timestamp":"2017-03-31 13:27:00"},{"nodeID":"270625","text":"Asserting","type":"YA","timestamp":"2017-03-31 13:27:01","scheme":"Asserting","schemeID":"74"},{"nodeID":"270626","text":"Asserting","type":"YA","timestamp":"2017-03-31 13:27:01","scheme":"Asserting","schemeID":"74"},{"nodeID":"270627","text":"Asserting","type":"YA","timestamp":"2017-03-31 13:27:01","scheme":"Asserting","schemeID":"74"},{"nodeID":"270628","text":"Asserting","type":"YA","timestamp":"2017-03-31 13:27:02","scheme":"Asserting","schemeID":"74"},{"nodeID":"270629","text":"Asserting","type":"YA","timestamp":"2017-03-31 13:27:02","scheme":"Asserting","schemeID":"74"},{"nodeID":"270630","text":"Default Transition","type":"TA","timestamp":"2017-03-31 13:27:02","scheme":"Default Transition","schemeID":"82"},{"nodeID":"270631","text":"Default Rephrase","type":"MA","timestamp":"2017-03-31 13:27:03","scheme":"Default Rephrase","schemeID":"144"},{"nodeID":"270632","text":"Default Illocuting","type":"YA","timestamp":"2017-03-31 13:27:03","scheme":"Default Illocuting","schemeID":"168"},{"nodeID":"270633","text":"Default Transition","type":"TA","timestamp":"2017-03-31 13:27:03","scheme":"Default Transition","schemeID":"82"},{"nodeID":"270634","text":"Default Transition","type":"TA","timestamp":"2017-03-31 13:27:03","scheme":"Default Transition","schemeID":"82"},{"nodeID":"270635","text":"Default Transition","type":"TA","timestamp":"2017-03-31 13:27:03","scheme":"Default Transition","schemeID":"82"},{"nodeID":"270636","text":"Default Inference","type":"RA","timestamp":"2017-03-31 13:27:03","scheme":"Default Inference","schemeID":"72"},{"nodeID":"270637","text":"Default Transition","type":"TA","timestamp":"2017-03-31 13:27:03","scheme":"Default Transition","schemeID":"82"},{"nodeID":"270638","text":"Default Inference","type":"RA","timestamp":"2017-03-31 13:27:04","scheme":"Default Inference","schemeID":"72"},{"nodeID":"270639","text":"Arguing","type":"YA","timestamp":"2017-03-31 13:27:04","scheme":"Arguing","schemeID":"80"},{"nodeID":"270640","text":"Pure Questioning","type":"YA","timestamp":"2017-03-31 13:27:04","scheme":"PureQuestioning","schemeID":"91"},{"nodeID":"270641","text":"Default Transition","type":"TA","timestamp":"2017-03-31 13:27:04","scheme":"Default Transition","schemeID":"82"},{"nodeID":"270642","text":"Maddie Groeger-Wilson can see both sides of it","type":"I","timestamp":"2017-03-31 13:27:04"},{"nodeID":"270643","text":"we all accept the realities of what we have to live with, and we'll all deal with it.","type":"I","timestamp":"2017-03-31 13:27:05"},{"nodeID":"270644","text":"either way Maddie Groeger-Wilson's quality of life is not going to dramatically drop down the drain. Maddie Groeger-Wilson will be fine, thanks.","type":"I","timestamp":"2017-03-31 13:27:05"},{"nodeID":"270645","text":"Asserting","type":"YA","timestamp":"2017-03-31 13:27:05","scheme":"Asserting","schemeID":"74"},{"nodeID":"270646","text":"Asserting","type":"YA","timestamp":"2017-03-31 13:27:05","scheme":"Asserting","schemeID":"74"},{"nodeID":"270647","text":"Asserting","type":"YA","timestamp":"2017-03-31 13:27:06","scheme":"Asserting","schemeID":"74"},{"nodeID":"270648","text":"Asserting","type":"YA","timestamp":"2017-03-31 13:27:06","scheme":"Asserting","schemeID":"74"},{"nodeID":"270649","text":"Default Inference","type":"RA","timestamp":"2017-03-31 13:27:06","scheme":"Default Inference","schemeID":"72"},{"nodeID":"270650","text":"Default Transition","type":"TA","timestamp":"2017-03-31 13:27:07","scheme":"Default Transition","schemeID":"82"},{"nodeID":"270651","text":"Arguing","type":"YA","timestamp":"2017-03-31 13:27:07","scheme":"Arguing","schemeID":"80"},{"nodeID":"270652","text":"Default Transition","type":"TA","timestamp":"2017-03-31 13:27:07","scheme":"Default Transition","schemeID":"82"},{"nodeID":"270653","text":"Arguing","type":"YA","timestamp":"2017-03-31 13:27:07","scheme":"Arguing","schemeID":"80"},{"nodeID":"270654","text":"Default Rephrase","type":"MA","timestamp":"2017-03-31 13:27:07","scheme":"Default Rephrase","schemeID":"144"},{"nodeID":"270655","text":"Default Illocuting","type":"YA","timestamp":"2017-03-31 13:27:07","scheme":"Default Illocuting","schemeID":"168"},{"nodeID":"270656","text":"Default Transition","type":"TA","timestamp":"2017-03-31 13:27:07","scheme":"Default Transition","schemeID":"82"},{"nodeID":"270657","text":"Default Transition","type":"TA","timestamp":"2017-03-31 13:27:07","scheme":"Default Transition","schemeID":"82"},{"nodeID":"270658","text":"Poppy Cleary will\/will not be fine","type":"I","timestamp":"2017-03-31 13:27:08"},{"nodeID":"270659","text":"Pure Questioning","type":"YA","timestamp":"2017-03-31 13:27:08","scheme":"PureQuestioning","schemeID":"91"},{"nodeID":"270660","text":"Default Transition","type":"TA","timestamp":"2017-03-31 13:27:08","scheme":"Default Transition","schemeID":"82"},{"nodeID":"270661","text":"Default Transition","type":"TA","timestamp":"2017-03-31 13:27:08","scheme":"Default Transition","schemeID":"82"},{"nodeID":"270662","text":"Disagreeing","type":"YA","timestamp":"2017-03-31 13:27:08","scheme":"Disagreeing","schemeID":"78"},{"nodeID":"270663","text":"Poppy Cleary will\/will not be resentful","type":"I","timestamp":"2017-03-31 13:27:09"},{"nodeID":"270664","text":"Pure Questioning","type":"YA","timestamp":"2017-03-31 13:27:09","scheme":"PureQuestioning","schemeID":"91"},{"nodeID":"270665","text":"Default Transition","type":"TA","timestamp":"2017-03-31 13:27:09","scheme":"Default Transition","schemeID":"82"},{"nodeID":"270666","text":"Poppy Cleary places a great importance on the prospect of owning a home in a city that Poppy Cleary wants to work in and that Poppy Cleary wants to live in for a lengthy period of time.","type":"I","timestamp":"2017-03-31 13:27:09"},{"nodeID":"270667","text":"owning a home and having that security in your life is of great importance to Poppy Cleary.","type":"I","timestamp":"2017-03-31 13:27:09"},{"nodeID":"270668","text":"Poppy Cleary doesn't see the problem with urban sprawl.","type":"I","timestamp":"2017-03-31 13:27:10"},{"nodeID":"270669","text":"Asserting","type":"YA","timestamp":"2017-03-31 13:27:10","scheme":"Asserting","schemeID":"74"},{"nodeID":"270670","text":"Default Transition","type":"TA","timestamp":"2017-03-31 13:27:10","scheme":"Default Transition","schemeID":"82"},{"nodeID":"270671","text":"Asserting","type":"YA","timestamp":"2017-03-31 13:27:11","scheme":"Asserting","schemeID":"74"},{"nodeID":"270672","text":"Disagreeing","type":"YA","timestamp":"2017-03-31 13:27:11","scheme":"Disagreeing","schemeID":"78"},{"nodeID":"270673","text":"Default Transition","type":"TA","timestamp":"2017-03-31 13:27:11","scheme":"Default Transition","schemeID":"82"},{"nodeID":"270674","text":"Asserting","type":"YA","timestamp":"2017-03-31 13:27:11","scheme":"Asserting","schemeID":"74"},{"nodeID":"270675","text":"Default Transition","type":"TA","timestamp":"2017-03-31 13:27:12","scheme":"Default Transition","schemeID":"82"},{"nodeID":"270676","text":"Default Conflict","type":"CA","timestamp":"2017-03-31 13:27:12","scheme":"Default Conflict","schemeID":"71"},{"nodeID":"270677","text":"Disagreeing","type":"YA","timestamp":"2017-03-31 13:27:12","scheme":"Disagreeing","schemeID":"78"},{"nodeID":"270678","text":"Asserting","type":"YA","timestamp":"2017-03-31 13:27:12","scheme":"Asserting","schemeID":"74"},{"nodeID":"270679","text":"Default Transition","type":"TA","timestamp":"2017-03-31 13:27:13","scheme":"Default Transition","schemeID":"82"},{"nodeID":"270680","text":"Asserting","type":"YA","timestamp":"2017-03-31 13:27:13","scheme":"Asserting","schemeID":"74"},{"nodeID":"270681","text":"Asserting","type":"YA","timestamp":"2017-03-31 13:27:13","scheme":"Asserting","schemeID":"74"},{"nodeID":"270682","text":"Default Transition","type":"TA","timestamp":"2017-03-31 13:27:14","scheme":"Default Transition","schemeID":"82"},{"nodeID":"270683","text":"Default Inference","type":"RA","timestamp":"2017-03-31 13:27:14","scheme":"Default Inference","schemeID":"72"},{"nodeID":"270684","text":"Arguing","type":"YA","timestamp":"2017-03-31 13:27:14","scheme":"Arguing","schemeID":"80"},{"nodeID":"270685","text":"Default Transition","type":"TA","timestamp":"2017-03-31 13:27:14","scheme":"Default Transition","schemeID":"82"},{"nodeID":"270686","text":"Default Rephrase","type":"MA","timestamp":"2017-03-31 13:27:14","scheme":"Default Rephrase","schemeID":"144"},{"nodeID":"270687","text":"Default Illocuting","type":"YA","timestamp":"2017-03-31 13:27:14","scheme":"Default Illocuting","schemeID":"168"}],"edges":[{"edgeID":"328240","fromID":"270592","toID":"268943","formEdgeID":null},{"edgeID":"328241","fromID":"268949","toID":"270592","formEdgeID":null},{"edgeID":"328242","fromID":"268946","toID":"270593","formEdgeID":null},{"edgeID":"328243","fromID":"270593","toID":"268949","formEdgeID":null},{"edgeID":"328244","fromID":"270594","toID":"270590","formEdgeID":null},{"edgeID":"328245","fromID":"268953","toID":"270594","formEdgeID":null},{"edgeID":"328246","fromID":"270595","toID":"268953","formEdgeID":null},{"edgeID":"328247","fromID":"268956","toID":"270595","formEdgeID":null},{"edgeID":"328248","fromID":"270596","toID":"270591","formEdgeID":null},{"edgeID":"328249","fromID":"268959","toID":"270596","formEdgeID":null},{"edgeID":"328250","fromID":"268949","toID":"270597","formEdgeID":null},{"edgeID":"328251","fromID":"270597","toID":"268956","formEdgeID":null},{"edgeID":"328252","fromID":"268956","toID":"270598","formEdgeID":null},{"edgeID":"328253","fromID":"270598","toID":"268959","formEdgeID":null},{"edgeID":"328254","fromID":"270601","toID":"270599","formEdgeID":null},{"edgeID":"328255","fromID":"268970","toID":"270601","formEdgeID":null},{"edgeID":"328256","fromID":"270602","toID":"268964","formEdgeID":null},{"edgeID":"328257","fromID":"268973","toID":"270602","formEdgeID":null},{"edgeID":"328258","fromID":"270603","toID":"270600","formEdgeID":null},{"edgeID":"328259","fromID":"268976","toID":"270603","formEdgeID":null},{"edgeID":"328260","fromID":"270604","toID":"268966","formEdgeID":null},{"edgeID":"328261","fromID":"268979","toID":"270604","formEdgeID":null},{"edgeID":"328262","fromID":"268959","toID":"270605","formEdgeID":null},{"edgeID":"328263","fromID":"270605","toID":"268967","formEdgeID":null},{"edgeID":"328264","fromID":"270605","toID":"270606","formEdgeID":null},{"edgeID":"328265","fromID":"270606","toID":"270591","formEdgeID":null},{"edgeID":"328266","fromID":"268967","toID":"270607","formEdgeID":null},{"edgeID":"328267","fromID":"270607","toID":"268970","formEdgeID":null},{"edgeID":"328268","fromID":"270599","toID":"270608","formEdgeID":null},{"edgeID":"328269","fromID":"270608","toID":"270591","formEdgeID":null},{"edgeID":"328270","fromID":"270607","toID":"270609","formEdgeID":null},{"edgeID":"328271","fromID":"270609","toID":"270608","formEdgeID":null},{"edgeID":"328272","fromID":"268970","toID":"270610","formEdgeID":null},{"edgeID":"328273","fromID":"270610","toID":"268973","formEdgeID":null},{"edgeID":"328274","fromID":"268973","toID":"270611","formEdgeID":null},{"edgeID":"328275","fromID":"270611","toID":"268976","formEdgeID":null},{"edgeID":"328276","fromID":"268964","toID":"270612","formEdgeID":null},{"edgeID":"328277","fromID":"270612","toID":"270600","formEdgeID":null},{"edgeID":"328278","fromID":"268964","toID":"270613","formEdgeID":null},{"edgeID":"328279","fromID":"270613","toID":"268966","formEdgeID":null},{"edgeID":"328280","fromID":"268973","toID":"270614","formEdgeID":null},{"edgeID":"328281","fromID":"270614","toID":"268979","formEdgeID":null},{"edgeID":"328282","fromID":"270615","toID":"270612","formEdgeID":null},{"edgeID":"328283","fromID":"270611","toID":"270615","formEdgeID":null},{"edgeID":"328284","fromID":"270614","toID":"270616","formEdgeID":null},{"edgeID":"328285","fromID":"270616","toID":"270613","formEdgeID":null},{"edgeID":"328286","fromID":"270618","toID":"268993","formEdgeID":null},{"edgeID":"328287","fromID":"268996","toID":"270618","formEdgeID":null},{"edgeID":"328288","fromID":"270619","toID":"270617","formEdgeID":null},{"edgeID":"328289","fromID":"268999","toID":"270619","formEdgeID":null},{"edgeID":"328290","fromID":"270620","toID":"268996","formEdgeID":null},{"edgeID":"328291","fromID":"269002","toID":"270620","formEdgeID":null},{"edgeID":"328292","fromID":"268979","toID":"270621","formEdgeID":null},{"edgeID":"328293","fromID":"270621","toID":"269002","formEdgeID":null},{"edgeID":"328294","fromID":"269002","toID":"270622","formEdgeID":null},{"edgeID":"328295","fromID":"270622","toID":"268999","formEdgeID":null},{"edgeID":"328296","fromID":"270625","toID":"269006","formEdgeID":null},{"edgeID":"328297","fromID":"269012","toID":"270625","formEdgeID":null},{"edgeID":"328298","fromID":"270626","toID":"270623","formEdgeID":null},{"edgeID":"328299","fromID":"269015","toID":"270626","formEdgeID":null},{"edgeID":"328300","fromID":"270627","toID":"270624","formEdgeID":null},{"edgeID":"328301","fromID":"269018","toID":"270627","formEdgeID":null},{"edgeID":"328302","fromID":"270628","toID":"269009","formEdgeID":null},{"edgeID":"328303","fromID":"269021","toID":"270628","formEdgeID":null},{"edgeID":"328304","fromID":"270629","toID":"269010","formEdgeID":null},{"edgeID":"328305","fromID":"269024","toID":"270629","formEdgeID":null},{"edgeID":"328306","fromID":"268999","toID":"270630","formEdgeID":null},{"edgeID":"328307","fromID":"270630","toID":"269012","formEdgeID":null},{"edgeID":"328308","fromID":"269006","toID":"270631","formEdgeID":null},{"edgeID":"328309","fromID":"270631","toID":"270617","formEdgeID":null},{"edgeID":"328310","fromID":"270630","toID":"270632","formEdgeID":null},{"edgeID":"328311","fromID":"270632","toID":"270631","formEdgeID":null},{"edgeID":"328312","fromID":"268999","toID":"270633","formEdgeID":null},{"edgeID":"328313","fromID":"270633","toID":"269015","formEdgeID":null},{"edgeID":"328314","fromID":"269015","toID":"270634","formEdgeID":null},{"edgeID":"328315","fromID":"270634","toID":"269018","formEdgeID":null},{"edgeID":"328316","fromID":"269018","toID":"270635","formEdgeID":null},{"edgeID":"328317","fromID":"270635","toID":"269021","formEdgeID":null},{"edgeID":"328318","fromID":"269009","toID":"270636","formEdgeID":null},{"edgeID":"328319","fromID":"270636","toID":"270624","formEdgeID":null},{"edgeID":"328320","fromID":"269021","toID":"270637","formEdgeID":null},{"edgeID":"328321","fromID":"270637","toID":"269024","formEdgeID":null},{"edgeID":"328322","fromID":"269009","toID":"270638","formEdgeID":null},{"edgeID":"328323","fromID":"270638","toID":"269010","formEdgeID":null},{"edgeID":"328324","fromID":"270637","toID":"270639","formEdgeID":null},{"edgeID":"328325","fromID":"270639","toID":"270638","formEdgeID":null},{"edgeID":"328326","fromID":"270640","toID":"269038","formEdgeID":null},{"edgeID":"328327","fromID":"269040","toID":"270640","formEdgeID":null},{"edgeID":"328328","fromID":"269024","toID":"270641","formEdgeID":null},{"edgeID":"328329","fromID":"270641","toID":"269040","formEdgeID":null},{"edgeID":"328330","fromID":"270645","toID":"269043","formEdgeID":null},{"edgeID":"328331","fromID":"269048","toID":"270645","formEdgeID":null},{"edgeID":"328332","fromID":"270646","toID":"270642","formEdgeID":null},{"edgeID":"328333","fromID":"269051","toID":"270646","formEdgeID":null},{"edgeID":"328334","fromID":"270647","toID":"270643","formEdgeID":null},{"edgeID":"328335","fromID":"269054","toID":"270647","formEdgeID":null},{"edgeID":"328336","fromID":"270648","toID":"270644","formEdgeID":null},{"edgeID":"328337","fromID":"269057","toID":"270648","formEdgeID":null},{"edgeID":"328338","fromID":"269043","toID":"270649","formEdgeID":null},{"edgeID":"328339","fromID":"270649","toID":"270642","formEdgeID":null},{"edgeID":"328340","fromID":"269048","toID":"270650","formEdgeID":null},{"edgeID":"328341","fromID":"270650","toID":"269051","formEdgeID":null},{"edgeID":"328342","fromID":"270650","toID":"270651","formEdgeID":null},{"edgeID":"328343","fromID":"270651","toID":"270649","formEdgeID":null},{"edgeID":"328344","fromID":"269040","toID":"270652","formEdgeID":null},{"edgeID":"328345","fromID":"270652","toID":"269048","formEdgeID":null},{"edgeID":"328346","fromID":"270635","toID":"270653","formEdgeID":null},{"edgeID":"328347","fromID":"270653","toID":"270636","formEdgeID":null},{"edgeID":"328348","fromID":"269043","toID":"270654","formEdgeID":null},{"edgeID":"328349","fromID":"270654","toID":"269038","formEdgeID":null},{"edgeID":"328350","fromID":"270652","toID":"270655","formEdgeID":null},{"edgeID":"328351","fromID":"270655","toID":"270654","formEdgeID":null},{"edgeID":"328352","fromID":"269051","toID":"270656","formEdgeID":null},{"edgeID":"328353","fromID":"270656","toID":"269054","formEdgeID":null},{"edgeID":"328354","fromID":"269054","toID":"270657","formEdgeID":null},{"edgeID":"328355","fromID":"270657","toID":"269057","formEdgeID":null},{"edgeID":"328356","fromID":"270659","toID":"270658","formEdgeID":null},{"edgeID":"328357","fromID":"269070","toID":"270659","formEdgeID":null},{"edgeID":"328358","fromID":"269057","toID":"270660","formEdgeID":null},{"edgeID":"328359","fromID":"270660","toID":"269070","formEdgeID":null},{"edgeID":"328360","fromID":"269070","toID":"270661","formEdgeID":null},{"edgeID":"328361","fromID":"270661","toID":"269073","formEdgeID":null},{"edgeID":"328362","fromID":"270661","toID":"270662","formEdgeID":null},{"edgeID":"328363","fromID":"270662","toID":"270643","formEdgeID":null},{"edgeID":"328364","fromID":"270664","toID":"270663","formEdgeID":null},{"edgeID":"328365","fromID":"269079","toID":"270664","formEdgeID":null},{"edgeID":"328366","fromID":"269073","toID":"270665","formEdgeID":null},{"edgeID":"328367","fromID":"270665","toID":"269079","formEdgeID":null},{"edgeID":"328368","fromID":"270669","toID":"270666","formEdgeID":null},{"edgeID":"328369","fromID":"269089","toID":"270669","formEdgeID":null},{"edgeID":"328370","fromID":"269079","toID":"270670","formEdgeID":null},{"edgeID":"328371","fromID":"270670","toID":"269089","formEdgeID":null},{"edgeID":"328372","fromID":"270671","toID":"269083","formEdgeID":null},{"edgeID":"328373","fromID":"269093","toID":"270671","formEdgeID":null},{"edgeID":"328374","fromID":"270672","toID":"269093","formEdgeID":null},{"edgeID":"328375","fromID":"269096","toID":"270672","formEdgeID":null},{"edgeID":"328376","fromID":"269089","toID":"270673","formEdgeID":null},{"edgeID":"328377","fromID":"270673","toID":"269096","formEdgeID":null},{"edgeID":"328378","fromID":"270674","toID":"270667","formEdgeID":null},{"edgeID":"328379","fromID":"269100","toID":"270674","formEdgeID":null},{"edgeID":"328380","fromID":"269096","toID":"270675","formEdgeID":null},{"edgeID":"328381","fromID":"270675","toID":"269100","formEdgeID":null},{"edgeID":"328382","fromID":"270667","toID":"270676","formEdgeID":null},{"edgeID":"328383","fromID":"270676","toID":"269083","formEdgeID":null},{"edgeID":"328384","fromID":"270675","toID":"270677","formEdgeID":null},{"edgeID":"328385","fromID":"270677","toID":"270676","formEdgeID":null},{"edgeID":"328386","fromID":"270678","toID":"269085","formEdgeID":null},{"edgeID":"328387","fromID":"269106","toID":"270678","formEdgeID":null},{"edgeID":"328388","fromID":"269100","toID":"270679","formEdgeID":null},{"edgeID":"328389","fromID":"270679","toID":"269106","formEdgeID":null},{"edgeID":"328390","fromID":"270680","toID":"269086","formEdgeID":null},{"edgeID":"328391","fromID":"269110","toID":"270680","formEdgeID":null},{"edgeID":"328392","fromID":"270681","toID":"270668","formEdgeID":null},{"edgeID":"328393","fromID":"269113","toID":"270681","formEdgeID":null},{"edgeID":"328394","fromID":"269106","toID":"270682","formEdgeID":null},{"edgeID":"328395","fromID":"270682","toID":"269110","formEdgeID":null},{"edgeID":"328396","fromID":"269086","toID":"270683","formEdgeID":null},{"edgeID":"328397","fromID":"270683","toID":"269085","formEdgeID":null},{"edgeID":"328398","fromID":"270682","toID":"270684","formEdgeID":null},{"edgeID":"328399","fromID":"270684","toID":"270683","formEdgeID":null},{"edgeID":"328400","fromID":"269110","toID":"270685","formEdgeID":null},{"edgeID":"328401","fromID":"270685","toID":"269113","formEdgeID":null},{"edgeID":"328402","fromID":"270623","toID":"270686","formEdgeID":null},{"edgeID":"328403","fromID":"270686","toID":"270617","formEdgeID":null},{"edgeID":"328404","fromID":"270633","toID":"270687","formEdgeID":null},{"edgeID":"328405","fromID":"270687","toID":"270686","formEdgeID":null}],"locutions":[{"nodeID":"268946","personID":"510","timestamp":"2017-03-31 10:56:13","start":null,"end":null,"source":null},{"nodeID":"268949","personID":"510","timestamp":"2017-03-31 10:56:13","start":null,"end":null,"source":null},{"nodeID":"268953","personID":"510","timestamp":"2017-03-31 10:56:13","start":null,"end":null,"source":null},{"nodeID":"268956","personID":"510","timestamp":"2017-03-31 10:56:13","start":null,"end":null,"source":null},{"nodeID":"268959","personID":"510","timestamp":"2017-03-31 10:56:13","start":null,"end":null,"source":null},{"nodeID":"268967","personID":"3423","timestamp":"2017-03-31 10:56:13","start":null,"end":null,"source":null},{"nodeID":"268970","personID":"3423","timestamp":"2017-03-31 10:56:13","start":null,"end":null,"source":null},{"nodeID":"268973","personID":"3423","timestamp":"2017-03-31 10:56:13","start":null,"end":null,"source":null},{"nodeID":"268976","personID":"3423","timestamp":"2017-03-31 10:56:13","start":null,"end":null,"source":null},{"nodeID":"268979","personID":"3423","timestamp":"2017-03-31 10:56:13","start":null,"end":null,"source":null},{"nodeID":"268996","personID":"510","timestamp":"2017-03-31 10:56:13","start":null,"end":null,"source":null},{"nodeID":"268999","personID":"510","timestamp":"2017-03-31 10:56:13","start":null,"end":null,"source":null},{"nodeID":"269002","personID":"510","timestamp":"2017-03-31 10:56:13","start":null,"end":null,"source":null},{"nodeID":"269012","personID":"3421","timestamp":"2017-03-31 10:56:13","start":null,"end":null,"source":null},{"nodeID":"269015","personID":"3421","timestamp":"2017-03-31 10:56:13","start":null,"end":null,"source":null},{"nodeID":"269018","personID":"3421","timestamp":"2017-03-31 10:56:13","start":null,"end":null,"source":null},{"nodeID":"269021","personID":"3421","timestamp":"2017-03-31 10:56:13","start":null,"end":null,"source":null},{"nodeID":"269024","personID":"3421","timestamp":"2017-03-31 10:56:13","start":null,"end":null,"source":null},{"nodeID":"269040","personID":"510","timestamp":"2017-03-31 10:56:13","start":null,"end":null,"source":null},{"nodeID":"269048","personID":"3421","timestamp":"2017-03-31 10:56:13","start":null,"end":null,"source":null},{"nodeID":"269051","personID":"3421","timestamp":"2017-03-31 10:56:13","start":null,"end":null,"source":null},{"nodeID":"269054","personID":"3421","timestamp":"2017-03-31 10:56:13","start":null,"end":null,"source":null},{"nodeID":"269057","personID":"3421","timestamp":"2017-03-31 10:56:13","start":null,"end":null,"source":null},{"nodeID":"269070","personID":"510","timestamp":"2017-03-31 10:56:13","start":null,"end":null,"source":null},{"nodeID":"269073","personID":"3428","timestamp":"2017-03-31 10:56:13","start":null,"end":null,"source":null},{"nodeID":"269079","personID":"510","timestamp":"2017-03-31 10:56:13","start":null,"end":null,"source":null},{"nodeID":"269089","personID":"3428","timestamp":"2017-03-31 10:56:13","start":null,"end":null,"source":null},{"nodeID":"269093","personID":"3428","timestamp":"2017-03-31 10:56:13","start":null,"end":null,"source":null},{"nodeID":"269096","personID":"3428","timestamp":"2017-03-31 10:56:13","start":null,"end":null,"source":null},{"nodeID":"269100","personID":"3428","timestamp":"2017-03-31 10:56:13","start":null,"end":null,"source":null},{"nodeID":"269106","personID":"3428","timestamp":"2017-03-31 10:56:13","start":null,"end":null,"source":null},{"nodeID":"269110","personID":"3428","timestamp":"2017-03-31 10:56:13","start":null,"end":null,"source":null},{"nodeID":"269113","personID":"3428","timestamp":"2017-03-31 10:56:13","start":null,"end":null,"source":null},{"nodeID":"268946","personID":"510","timestamp":"2017-03-31 13:27:23","start":null,"end":null,"source":null},{"nodeID":"268949","personID":"510","timestamp":"2017-03-31 13:27:23","start":null,"end":null,"source":null},{"nodeID":"268953","personID":"510","timestamp":"2017-03-31 13:27:23","start":null,"end":null,"source":null},{"nodeID":"268956","personID":"510","timestamp":"2017-03-31 13:27:23","start":null,"end":null,"source":null},{"nodeID":"268959","personID":"510","timestamp":"2017-03-31 13:27:23","start":null,"end":null,"source":null},{"nodeID":"268967","personID":"3423","timestamp":"2017-03-31 13:27:23","start":null,"end":null,"source":null},{"nodeID":"268970","personID":"3423","timestamp":"2017-03-31 13:27:23","start":null,"end":null,"source":null},{"nodeID":"268973","personID":"3423","timestamp":"2017-03-31 13:27:23","start":null,"end":null,"source":null},{"nodeID":"268976","personID":"3423","timestamp":"2017-03-31 13:27:23","start":null,"end":null,"source":null},{"nodeID":"268979","personID":"3423","timestamp":"2017-03-31 13:27:23","start":null,"end":null,"source":null},{"nodeID":"268996","personID":"510","timestamp":"2017-03-31 13:27:23","start":null,"end":null,"source":null},{"nodeID":"268999","personID":"510","timestamp":"2017-03-31 13:27:23","start":null,"end":null,"source":null},{"nodeID":"269002","personID":"510","timestamp":"2017-03-31 13:27:23","start":null,"end":null,"source":null},{"nodeID":"269012","personID":"3421","timestamp":"2017-03-31 13:27:23","start":null,"end":null,"source":null},{"nodeID":"269015","personID":"3421","timestamp":"2017-03-31 13:27:23","start":null,"end":null,"source":null},{"nodeID":"269018","personID":"3421","timestamp":"2017-03-31 13:27:23","start":null,"end":null,"source":null},{"nodeID":"269021","personID":"3421","timestamp":"2017-03-31 13:27:23","start":null,"end":null,"source":null},{"nodeID":"269024","personID":"3421","timestamp":"2017-03-31 13:27:23","start":null,"end":null,"source":null},{"nodeID":"269040","personID":"510","timestamp":"2017-03-31 13:27:23","start":null,"end":null,"source":null},{"nodeID":"269048","personID":"3421","timestamp":"2017-03-31 13:27:23","start":null,"end":null,"source":null},{"nodeID":"269051","personID":"3421","timestamp":"2017-03-31 13:27:23","start":null,"end":null,"source":null},{"nodeID":"269054","personID":"3421","timestamp":"2017-03-31 13:27:23","start":null,"end":null,"source":null},{"nodeID":"269057","personID":"3421","timestamp":"2017-03-31 13:27:23","start":null,"end":null,"source":null},{"nodeID":"269070","personID":"510","timestamp":"2017-03-31 13:27:23","start":null,"end":null,"source":null},{"nodeID":"269073","personID":"3428","timestamp":"2017-03-31 13:27:23","start":null,"end":null,"source":null},{"nodeID":"269079","personID":"510","timestamp":"2017-03-31 13:27:23","start":null,"end":null,"source":null},{"nodeID":"269089","personID":"3428","timestamp":"2017-03-31 13:27:23","start":null,"end":null,"source":null},{"nodeID":"269093","personID":"3428","timestamp":"2017-03-31 13:27:23","start":null,"end":null,"source":null},{"nodeID":"269096","personID":"3428","timestamp":"2017-03-31 13:27:23","start":null,"end":null,"source":null},{"nodeID":"269100","personID":"3428","timestamp":"2017-03-31 13:27:23","start":null,"end":null,"source":null},{"nodeID":"269106","personID":"3428","timestamp":"2017-03-31 13:27:23","start":null,"end":null,"source":null},{"nodeID":"269110","personID":"3428","timestamp":"2017-03-31 13:27:23","start":null,"end":null,"source":null},{"nodeID":"269113","personID":"3428","timestamp":"2017-03-31 13:27:23","start":null,"end":null,"source":null}]}